{
  "id": "local_c0e66451eaf0",
  "title": "離經叛道：不按常理出牌的人如何改變世界",
  "category": "其他",
  "total_pages": 257,
  "toc": [
    {
      "level": 1,
      "title": "推薦序",
      "page": 5
    },
    {
      "level": 1,
      "title": "1 創造性毀滅：違背常規的風險",
      "page": 10
    },
    {
      "level": 2,
      "title": "打破默認的規則",
      "page": 13
    },
    {
      "level": 2,
      "title": "雄心壯志的兩面性",
      "page": 18
    },
    {
      "level": 2,
      "title": "正確的特質",
      "page": 22
    },
    {
      "level": 2,
      "title": "為何風險就像股票投資組合",
      "page": 27
    },
    {
      "level": 1,
      "title": "2 盲目的發明家與目光狹隘的投資者： 識別原創想法的藝術和科學",
      "page": 13
    },
    {
      "level": 2,
      "title": "在創意的鋼絲繩上漫步",
      "page": 39
    },
    {
      "level": 2,
      "title": "親吻青蛙",
      "page": 43
    },
    {
      "level": 2,
      "title": "原型的囚徒和目光狹隘的偏好",
      "page": 46
    },
    {
      "level": 2,
      "title": "經驗是一把雙刃劍",
      "page": 50
    },
    {
      "level": 2,
      "title": "直覺的偶然性，又或者說史蒂夫·喬布斯錯在哪裡",
      "page": 55
    },
    {
      "level": 2,
      "title": "激情的風險",
      "page": 59
    },
    {
      "level": 2,
      "title": "如何儘可能地選對創意",
      "page": 61
    },
    {
      "level": 1,
      "title": "3 孤立無援：向上級說出真實想法",
      "page": 20
    },
    {
      "level": 2,
      "title": "沒有地位的權力",
      "page": 69
    },
    {
      "level": 2,
      "title": "邁出最差的一步：賽瑞克效應（The Sarick Effect）",
      "page": 72
    },
    {
      "level": 2,
      "title": "陌生產生輕視",
      "page": 77
    },
    {
      "level": 2,
      "title": "在離開之前放棄",
      "page": 81
    },
    {
      "level": 2,
      "title": "發聲+女性身份，雙重少數身份帶來雙重風險",
      "page": 86
    },
    {
      "level": 2,
      "title": "未選擇的路",
      "page": 88
    },
    {
      "level": 1,
      "title": "4 急躁的愚人：選擇時機、戰術性拖延和先動劣勢",
      "page": 26
    },
    {
      "level": 2,
      "title": "另一個達·芬奇密碼",
      "page": 96
    },
    {
      "level": 2,
      "title": "拖延的紀律",
      "page": 98
    },
    {
      "level": 2,
      "title": "自由飛翔和祈禱",
      "page": 100
    },
    {
      "level": 2,
      "title": "開拓者和定居者",
      "page": 102
    },
    {
      "level": 2,
      "title": "創造力的兩個生命週期：年輕的天才和年長的大師",
      "page": 107
    },
    {
      "level": 1,
      "title": "5 金髮姑娘和特洛伊木馬：創造和維護聯盟",
      "page": 31
    },
    {
      "level": 2,
      "title": "微小差異的自我陶醉",
      "page": 115
    },
    {
      "level": 2,
      "title": "溫和的激進分子",
      "page": 119
    },
    {
      "level": 2,
      "title": "與敵人而不是友敵結盟",
      "page": 124
    },
    {
      "level": 2,
      "title": "熟悉產生美",
      "page": 130
    },
    {
      "level": 2,
      "title": "西部是如何勝利的",
      "page": 134
    },
    {
      "level": 2,
      "title": "攜手前進：在衝突陣營之間結成聯盟",
      "page": 136
    },
    {
      "level": 1,
      "title": "6 給叛逆一個理由：兄弟姐妹、父母和榜樣是如何影響你的創新性的",
      "page": 36
    },
    {
      "level": 2,
      "title": "生而反叛",
      "page": 146
    },
    {
      "level": 2,
      "title": "選窩（Niche Picking）：不爭之爭",
      "page": 148
    },
    {
      "level": 2,
      "title": "父母管得越來越松",
      "page": 151
    },
    {
      "level": 2,
      "title": "偉大的解釋",
      "page": 153
    },
    {
      "level": 2,
      "title": "不受待見的人：為什麼名詞比動詞好",
      "page": 156
    },
    {
      "level": 2,
      "title": "為什麼父母不是最好的榜樣",
      "page": 158
    },
    {
      "level": 1,
      "title": "7 再議團體迷思：強文化、狂熱崇拜和魔鬼擁護者的奧秘",
      "page": 39
    },
    {
      "level": 2,
      "title": "藍圖中的螺絲釘",
      "page": 167
    },
    {
      "level": 2,
      "title": "成長的煩惱：忠誠度文化的弊端",
      "page": 169
    },
    {
      "level": 2,
      "title": "“不同凡想”48文化",
      "page": 173
    },
    {
      "level": 2,
      "title": "你所知道的魔鬼",
      "page": 176
    },
    {
      "level": 2,
      "title": "找到一隻能在煤礦中報警的金絲雀",
      "page": 180
    },
    {
      "level": 2,
      "title": "當原則發生衝突",
      "page": 183
    },
    {
      "level": 2,
      "title": "真相大白的時刻",
      "page": 186
    },
    {
      "level": 2,
      "title": "移動者和塑造者",
      "page": 189
    },
    {
      "level": 1,
      "title": "8 逆流而行並保持穩定： 管控焦慮、冷漠、矛盾和憤怒",
      "page": 46
    },
    {
      "level": 2,
      "title": "負面思想的積極力量",
      "page": 193
    },
    {
      "level": 2,
      "title": "不要放棄信念",
      "page": 196
    },
    {
      "level": 2,
      "title": "外包激勵",
      "page": 200
    },
    {
      "level": 2,
      "title": "少數的力量",
      "page": 202
    },
    {
      "level": 2,
      "title": "燃燒的平臺",
      "page": 207
    },
    {
      "level": 2,
      "title": "表演必須繼續",
      "page": 211
    },
    {
      "level": 2,
      "title": "火上澆油",
      "page": 212
    },
    {
      "level": 2,
      "title": "採取行動，產生影響",
      "page": 216
    },
    {
      "level": 1,
      "title": "致謝微信dedao555",
      "page": 50
    }
  ],
  "intro": "目錄 推薦序♣ 1 創造性毀滅：違背常規的風險 打破默認的規則 雄心壯志的兩面性 正確的特質 為何風險就像股票投資組合 2 盲目的發明家與目光狹隘的投資者： 識別原創想法的藝術和科學 在創意的鋼絲繩上漫步 親吻青蛙....♣ 原型的囚徒和目光狹隘的偏好 經驗是一把雙刃劍 直覺的偶然性，又或者說史蒂夫·喬布斯錯在哪裡 激情的風險 如何儘可能地選對創意 3 孤立無援：向上級說出真實想法 沒有地位的權力 邁出最差的一步：賽瑞克效應（The Sarick Effect） 陌生產生輕視 在離開之前放棄 發聲+女性身份，雙重少數身份帶來雙重風險 未選擇的路 4 急躁的愚人：選擇時機、戰術性拖延和先動劣勢♣ 另一個達·芬奇密碼 拖延的紀律 自由飛翔和祈禱 開拓者和定居者 創造力的兩個生命週期：年輕的天才和年長的大師 5 金髮姑娘和特洛伊木馬：創造和維護聯盟 微小差異的自我陶醉 溫和的激進分子 與敵人而不是友敵結盟 熟悉產生美 西部是如何勝利的 攜手前進：在衝突陣營之間結成聯盟 6 給叛逆一個理由：兄弟姐妹、父母和榜樣是如何影響你的創新性的 生而反叛....♣ 選窩（Niche Picking）：不爭之爭 父母管得越來越松 偉大的解釋 不受待見的人：為什麼名詞比動詞好 為什麼父母不是最好的榜樣 7 再議團體迷思：強文化、狂熱崇拜和魔鬼擁護者的奧秘 藍圖中的螺絲釘 成長的煩惱：忠誠度文化的弊端 “不同凡想”48文化 你所知道的魔鬼 找到一隻能在煤礦中報警的金絲雀 當原則發生衝突 真相大白的時刻 移動者和塑造者 8 逆流而行並保持穩定： 管控焦慮、冷漠、矛盾和憤怒 負面思想的積極力量 不要放棄信念 外包激勵 少數的力量 燃燒的平臺 表演必須繼續 火上澆油 採取行動，產生影響 致謝 參考文獻 ♣ 致那些離經叛道者—— 那些格格不入的反叛分子，那些惹是生非的傢伙， 如同方孔裡的園釘一樣是些異類，總是異想天開。 他們不滿條條框框，從不墨守成規。 你儘可以支持或反對他們，可以讚美或中傷他們， 但你唯一不能做的就是忽視他們。 因為他們改變了局面，他們推動了人類進步。 雖然有人視他們為瘋子，我們卻稱其為天才。 因為那些妄想改變世界的人，正在改變世界。 1 ——傑克·凱魯亞克（Jack Keroauc） 推薦序 謝麗爾·桑德伯格 臉書（Facebook）首席運營官 《向前一步》作者、LeanIn.Org創始人 亞當·格蘭特寫《離經叛道》一書再合適不過，因為他本人就是一 個離經叛道者。♣ 他是一位傑出的研究者，充滿熱情地探索能夠激勵他人的方法， 打破錯誤觀念，並向人們揭示真相。他是一位有見地的樂觀主義者， 為各種各樣的人——不管是家庭主婦、公司白領，還是社區工作者 ——提供洞見和建議，從而使他們明白如何才能創造出更加美好的世 界。他是一位樂於奉獻的朋友，給我鼓舞，讓我相信自己，並幫助我 明白如何有效地去捍衛自己的想法。 在我的生命旅程中，亞當是對我影響最大的人之一。通過閱讀這 本傑作的每一頁，你也同樣會從他那裡獲得啟發、靈感和支持。 錯誤觀念的打破者 傳統觀點認為，只有一些人天生具有創造力，而大多數人很少有 富有創新性的想法。一些人生來就要做領袖，而剩下的人僅僅能做追",
  "chapters": [
    {
      "title": "推薦序",
      "page": 5,
      "excerpt": "♣ 致那些離經叛道者—— 那些格格不入的反叛分子，那些惹是生非的傢伙， 如同方孔裡的園釘一樣是些異類，總是異想天開。 他們不滿條條框框，從不墨守成規。 你儘可以支持或反對他們，可以讚美或中傷他們， 但你唯一不能做的就是忽視他們。 因為他們改變了局面，他們推動了人類進步。 雖然有人視他們為瘋子，我們卻稱其為天才。 因為那些妄想改變世界的人，正在改變世界。 1 ——傑克·凱魯亞克（Jack Keroauc） 推薦序 謝麗爾·桑德伯格 臉書（Facebook）首席運營官 《向前一步》作者、LeanIn.Org創始人 亞當·格蘭特寫《離經叛道》一書再合適不過，因為他本人就是一 個離經叛道者。♣ 他是一位傑出的研究者，充滿熱情地探索能夠激勵他人的方法， 打破錯誤觀念，並向人們揭示真相。他是一位有見地的樂觀主義者， 為各種各樣的人——不管是家庭主婦、公司白領，還是社區工作者 ——提供洞見和建議，從而使他們明白如何才能創造出更加美好的世 界。他是一位樂於奉獻的朋友，給我鼓舞，讓我相信自己，並幫助我 明白如何有效地去捍衛自己的想法。 在我的生命旅程中，亞當是對我影響最大的人之一。通過閱讀這 本傑作的每一頁，你也同樣會從他那裡獲得啟發、靈感和支持。 錯誤觀念的打破者 傳統觀點認為，只有一些人天生具有創造力，而大多數人很少有 富有創新性的想法。一些人生來就要做領袖，而剩下的人僅僅能做追"
    },
    {
      "title": "1 創造性毀滅：違背常規的風險",
      "page": 10,
      "excerpt": "理性之人讓自己去適應這個世界 ［1］ ，非理性之人堅 持讓世界去適應自己。♣ 故一切進步皆依賴於非理性之人。 ——蕭伯納（George Bernard Shaw） 1 創造性毀滅：違背常規的風險 2008年一個涼爽的秋夜，4名學生決定做一項顛覆性的事業。他 們身負債務，而且佩戴的眼鏡不是丟失了就是弄壞了，他們十分惱火 要花這麼多錢去換一副新的眼鏡。其中一名學生已經戴著一副破舊的 眼鏡5年了，他用回形針將眼鏡框別在一起。他拒絕購買昂貴的新鏡 片，即便他的近視度數已經漲了兩次。♣ 當時，眼鏡巨擘陸遜梯卡集團（Luxottica）控制著80%以上的眼 鏡市場。要想使眼鏡賣得更便宜，這些學生需要推翻這一巨頭在眼鏡 業的支配地位。當時恰逢美捷步（Zappos）通過在線銷售鞋子改變了 鞋類市場，於是他們思忖著是否也可以將這種方式應用於眼鏡行業。 他們時不時地跟朋友們提到這個想法，但一次又一次地受到了強 烈的質疑。朋友們堅信沒人會在網上買眼鏡，因為顧客首先要試戴。 誠然，美捷步在網上銷售鞋子的想法獲得了成功，但這種模式沒能應 用於眼鏡業必定有原因。不斷有人告訴他們：“如果這是個好主意， 一定早就有人做了。” 這些學生在電子商務和技術方面沒有任何背景，更不用說在零 售、時尚或服飾行業上。儘管別人一再認為他們的想法很瘋狂，他們 還是放棄了可以賺很多錢的工作，開始創業。正常要賣500美元的眼 鏡在他們的網站上只要95美元，而且每賣出一副眼鏡，他們就要捐贈 一副眼鏡給發展中國家。 他們所有的業務都依賴於網站運營。如果沒有網站，顧客就不可 能瀏覽和購買他們的產品。他們匆匆忙忙拼湊成一個網站，最終在凌 晨4點讓它成功上線，這距公司2010年2月的成立日只差一天時間。 他們把公司命名為沃比·帕克（Warby Parker） ［2］ ，這個名字是將"
    },
    {
      "title": "打破默認的規則",
      "page": 13,
      "excerpt": "很多年前，心理學家發現有兩種通往成功的路徑：一種是墨守成 規，一種是創新。墨守成規是指遵循大多數人所走的傳統常規道路並 維持現狀。創新則是指走少數人走過的路，堅信一系列有違常規，但 最終能使事情變得更佳的新想法或價值觀。 當然，沒有任何事物是完全原創的，因為我們所有的想法都受到 我們周圍世界的影響。無論有意還是無意，我們無時無刻不在借用。 我們都受到盜竊癖（kleptomania） ［3］ 的影響，即不經意地記住別 人的想法並把它們當成是自己的。在我看來，創新包括提出並推進一 種想法，這種想法在某一領域中不同尋常，並且有得以改進的潛力。 創新本身始於創造力：想出一個既新穎又實用的概念。但創新又 不止於此。創新者是指那些主動採取行動使他們的想法成為現實的 人。沃比帕克的創建者們擁有創新精神，他們構想出一個不同於傳統 的在線銷售眼鏡的方式。但當他們切實採取行動使眼鏡既能方便購 買，又價廉物美時，他們成了創新者。 這本書要講的是我們可以怎樣更具創新精神。令人意想不到的 是，你選擇哪種網頁瀏覽器竟可以透露出你的創新程度。 打破默認的規則 不久前，經濟學家邁克爾·豪斯曼（Michael Housman）主持了一 個項目，研究為什麼有些客戶服務代表在他們工作崗位上工作的時間 比其他人更久。豪斯曼掌握了3萬餘名員工的數據信息，他們的工作 是處理來自銀行、航空公司和手機公司的呼叫業務。豪斯曼猜測從這 些員工以前的工作經歷中可能會找到一些關於他們工作忠誠度的線 索。他猜測之前有過跳槽歷史的員工會辭職得更快，但事實上他們並 沒有；同過去5年一直做同一份工作的員工相比，在過去5年中做過5 份不同工作的員工辭職的概率並不會更高。 在尋找其他線索的過程中，他注意到了其團隊獲得的關於僱員在 申請工作時使用哪種瀏覽器登錄的信息。一時興起，他測試了關於瀏 覽器的選擇是否與他們辭職有關。他未曾料到會在這兩者間找到任何 相關性，因為我們常常認為選擇用哪種瀏覽器純粹是個人喜好的問 題。但當他看到了結果，他驚呆了：使用Firefox或Chrome瀏覽器的 員工堅守在某一崗位上的時間要比那些使用IE瀏覽器或Safari瀏覽器 的員工長15%。 豪斯曼認為這只是一個巧合，於是又對工作缺勤情況做了相同的 分析。結果竟與之前相同：使用Firefox瀏覽器和Chrome瀏覽器的員 工，其缺勤率比使用IE瀏覽器和Safari瀏覽器的員工要低19%。 然後他觀察了僱員的業績水平。他的研究團隊收集了關於員工在 銷售、客戶滿意度、平均通話時長方面近300萬個數據點。使用 Firefox瀏覽器和Chrome瀏覽器的員工有著明顯更高的銷售額，通話 時間更短。他們的客戶滿意度也更高：使用Firefox瀏覽器和Chrome 瀏覽器的員工在90個工作日內達到的客戶滿意度，需要那些用IE瀏覽 器和Safari瀏覽器的員工花上120個工作日才能達到。 瀏覽器本身並不是造成他們忠於職守、表現踏實並獲得業績成功 的原因。相反，正是他們使用瀏覽器的偏好，釋放出他們有哪些習慣 的信號。為什麼使用Firefox瀏覽器和Chrome瀏覽器的員工在每一個 指標上都更投入，表現更好呢？ 表面上看起來，顯而易見的答案是他們更精通計算機技術。於是 我問豪斯曼他能否對此進行探索。員工們於是全部做了計算機水平測 試，這一測試旨在評估他們在鍵盤快捷鍵、軟件程序和硬件方面的知 識水平，並對他們的打字速度進行了計時測試。但結果是，使用 Firefox瀏覽器和Chrome瀏覽器的員工群體並沒有被證明有更多的計 算機專業知識，他們打字也並不更快或更準"
    },
    {
      "title": "雄心壯志的兩面性",
      "page": 18,
      "excerpt": "雄心壯志的兩面性 接受默認常規的壓力開始得遠遠比我們意識到的要早。在思考那 些可能長大後會做出一番偉業的人時，你首先想到的可能是神童。這 些天才兩歲時學習閱讀，四歲時彈奏巴赫的曲目，六歲時學微積分， 八歲時可以流利地說七種語言。他們的同學感到不寒而慄，十分羨慕 他們的才能；他們的父母充滿喜悅，如同彩票中獎。但套用T.S.艾略 特（T.S.Eliot）的話說，他們的職業生涯往往並不是伴隨著轟動的巨 響聲，而是在嗚咽聲中結束的。 結果證明，很少有神童能夠在長大後改變世界。當心理學家對歷 史上最知名和最具影響力的人進行研究時，他們發現其中的很多人在 兒童時期並沒有什麼天賦。如果將一大群神童聚集起來，並追蹤他們 整個人生，你會發現，他們並不勝過同樣家庭水平中沒有他們早熟的 那些同齡人。 憑直覺來看，這似乎是說得通的。我們假設這些孩子只是在學習 書本知識上有天賦，但卻缺乏實際應用的智慧。雖然他們智力超群， 但卻缺乏在社會上生存所需要的社交、情感、實踐技能。但如果我們 看一看證據，這樣的解釋並站不住腳：受社會和情感問題困擾的天才 兒童不到四分之一，絕大多數都能夠很好地適應社會，雞尾酒會給他 們帶來的愉悅感並不亞於拼字遊戲。 儘管神童往往有更多才能和更大的雄心壯志，但阻止他們推動世 界前進的是：他們並沒有嘗試著離經叛道。他們在卡內基音樂廳演 出，在奧林匹克競賽中獲獎，在成為國際象棋冠軍的同時，悲慘的事 情發生了：熟能生巧，但這種熟練並不能催生出新的事物。天才神童 學習彈奏莫扎特優美的旋律和貝多芬優美的交響曲，但他們從來不會 創作自己的原創音樂。他們將自己的精力集中於學習現有的科學知 識，而不是得出新的見解。他們遵守遊戲的既定規則，而不是發明自 己的規則或自己的遊戲。在整個過程中，他們努力去贏得父母的讚許 以及老師的表揚。 研究表明，最有創造力的孩子最不可能成為老師的寵兒。在一項 研究中，小學教師列出自己最喜歡和最不喜歡的學生，然後根據一系 列特徵評價兩組學生。最不喜歡的學生是那些不墨守成規者，他們自 己定規則。教師往往對極富創造力的學生區別對待，把他們視為麻煩 製造者。因而，許多孩子很快就學著去適應這種程序，把自己獨創新 穎的想法放在心裡。用作家威廉姆·德雷謝維奇（William Deresiewicz）的話來說，他們成了世界上最優秀的綿羊。 這些神童長大後通常會成為各自領域的專家和各自組織中的領 導。然而，“僅有一小部分天才兒童最終成為革命性的創造者” ［7］ 。 心理學家埃倫·溫納（Ellen Winner）感慨道：“那一小部分人必須經 歷一場痛苦的轉型，從一個在既定領域中毫不費力就能迅速適應的孩 子，轉變為最終重新改寫某一領域的成年人。” 大多數天才從未完成這樣的轉型。他們以平庸的方式發揮他們非 凡的能力，做好他們的工作，而不去質疑默認的常規，也不去打破現 狀。他們的風險投資組合失去了平衡：在他們涉足的每一領域，為保 險起見，他們都遵循傳統的成功路徑。他們成為醫治疾病的醫生，而 不是為改善漏洞百出的體系而鬥爭，結果許多患者根本消費不起醫療 服務。作為律師，他們為違反過時法律的客戶進行辯護，卻不嘗試改 變法律本身。作為教師，他們設計吸引學生的代數課，但不去質疑代 數是否是學生們必須學的。雖然有了他們，世界得以平穩地運行，但 他們也使得世界止步不前。 神童因為渴望成就而故步自封。固然，想要成功的動力造就了世 界上許多最偉大的成就。當我們下定決心成為出類拔萃的人時，我們 就有了更加努力、更加刻苦、變得更加聰明的動力。但當這個世界已 經收穫了許多重大成績，創新的"
    },
    {
      "title": "正確的特質",
      "page": 22,
      "excerpt": "而我們由於害怕打破原有格局而止步不前。在美國食品藥品管理局近 千名科學家中，超過40%的人擔心，在公開場合談論安全問題可能會 遭到報復。在一家技術公司的4萬餘名的員工中，有一半認為在工作 中發表反對意見是不好的。當對諮詢、金融服務、媒體、醫藥、廣告 公司的員工進行採訪時，85%的人承認最好在一些重要問題上保持沉 默，不要向老闆發表自己的看法，因為他們希望在自身形象、人際關 係和職業生涯等方面規避風險。 當你最近一次產生了一個原創想法時，你是如何處理它的？儘管 在美國這片土地上，我們尊重個性和獨特的自我表達，但由於追求成 功和害怕失敗，我們中的大多數人選擇適應而非脫穎而出。托馬斯·傑 斐遜（Thomas Jefferson）曾建議：“在形式方面，可以隨波逐流；但 在原則問題上，要堅如磐石。”希望獲得成功的壓力使我們做了恰恰 相反的事情，我們只是採用膚淺的方式顯示我們具有叛逆精神，例如 戴上領結，穿著鮮豔的紅鞋，但事實上，我們並不敢冒風險真正地離 經叛道。當涉及我們頭腦中根深蒂固的思想以及我們心中的核心價值 觀時，我們抑制了這些想法。“生活中有創新精神的人少之又少。” ［11］ 知名高管麥勒迪·霍布森（Mellody Hobson）說道，因為人們都 不敢“說出來，站出來”。那麼那些將創新精神付諸有效行動的人有哪 些習慣呢？ 正確的特質 要成為一個離經叛道者，需要承擔極大的風險。這種想法已經深 入我們的文化、骨髓和靈魂之中，以至於我們很少會停下來去思考它 是否正確。我們崇拜諸如尼爾·阿姆斯特朗（Neil Armstrong） 3 和薩 莉·賴德（Sally Ride） 4 之類的宇航員，崇拜他們身上擁有的“正確的 特質”——離開人類長期居住的星球去太空中大膽冒險的勇氣。我們 讚頌諸如聖雄甘地（Mahatma Gandhi）和馬丁·路德·金（Martin Luther King， Jr.）這樣的英雄人物，他們充滿堅定的信念，誓死捍 衛他們所珍視的道德原則。我們將史蒂夫·喬布斯（Steve Jobs）和比 爾·蓋茨（Bill Gates）奉為偶像，崇拜他們有勇氣中途輟學，全身心 地投入創業，把自己關在車庫中，努力將頭腦中的想法變為現實。 當我們驚歎這些給世界帶來創造力和重大改變的創新者時，我們 往往以為他們是不同尋常的人。如同一些幸運的人，他們生來就有基 因變異，使他們不受諸如癌症、肥胖、艾滋病等疾病的影響。同樣， 我們認為偉大的創造者生來對風險就有免疫能力。他們註定會勇敢地 面對不確定性，忽視來自社會的阻力；他們壓根就不擔心做離經叛道 者所要付出的代價。他們註定成為打破舊習者、反叛者、革命者、搗 亂者、標新立異者以及唱反調者，他們絲毫不受恐懼、拒絕和嘲諷的 影響。 “企業家”（entrepreneur） ［12］ 這一概念是由經濟學家理查德· 坎蒂隆（Richard Cantillon）提出的，其字面意思是“風險承擔 者”（bearer of risk）。當我們讀了沃比帕克驚人崛起的故事，我們就 會清晰地感知到這層含義。如同所有偉大的創造者、創新者和變革 者，創立者們因為願意堅持信念而改變了世界。畢竟，如果你不盡最 大努力擊球，你就不可能成功打出一個全壘打。 難道不是嗎？ ※ ※ ※ 在沃比帕克成立6個月之前，創始人之一尼爾·布盧門撒爾（Neil Blumenthal）正在沃頓商學院的教室裡聽我上課。他個子高，留著黑 色捲髮，待人彬彬有禮，沉穩但不失活力。他曾在一家非營利機構工 作過，由衷地希望能使這個世界變得更美好。當他向我宣傳這家公司 時，同許多其他"
    },
    {
      "title": "為何風險就像股票投資組合",
      "page": 27,
      "excerpt": "穩而不是冒風險呢？ 為何風險就像股票投資組合 半個世紀之前，密歇根大學心理學家克萊德·庫姆斯（Clyde Coombs）提出一個具有創新性的風險理論：在股票市場，如果你決 定進行一項風險性投資，那麼你就需要謹慎地對待其他投資來保護自 己。庫姆斯提出，在日常生活中，成功人士對待風險也同樣如此，他 們在組合中平衡各項風險。當在一個領域鋌而走險，我們可以通過在 其他領域謹慎行事來降低整體風險水平。如果你打算豪賭一把，那麼 在開往賭場的路上，你也許會放慢速度，低於限速行駛。 風險組合 ［17］ 可以用來說明為何人們通常在生活中的一個方面 表現得極富創意，而在其他方面則相當傳統。棒球俱樂部總經理布蘭 奇·瑞基（Branch Rickey）大膽地將傑基·羅賓森（Jackie Robinson） 5 帶入球場，打破了種族隔離的障礙，但布蘭奇在工作日外的週日不 去球場，不說任何髒話，也滴酒不沾。T.S.艾略特的代表作《荒原》 （The Waste Land ）被譽為20世紀最重要的詩歌之一。但在1922年 發表之後，艾略特一直在倫敦的一家銀行工作，一直到1925年，因為 他不想冒任何經濟風險。小說家阿道司·赫胥黎（Aldous Huxley）去 他的辦公室拜訪後評論道，艾略特是“所有銀行職員中最有銀行職員 氣質的人”。當艾略特最終辭去了這一職務，他仍舊沒有自立門戶。 在之後的40年裡，他一直在一家出版社工作，這使他的生活穩定而有 條理，在業餘時間裡他也創作詩歌。正如寶麗來（Polaroid）創始人 埃德溫·蘭德（Edwin Land）所說，“沒有人能在一個領域是完全原創 的，除非他對於其他領域的態度都是固定的，從而在情感和社會上都 有安全感”。 但白天的工作難道不會分散我們做自己最擅長之事的精力嗎？常 識告訴我們，如果不投入大量時間和精力，創意性的成就很難實現， 如果沒有集中精力努力工作，公司也不會繁榮昌盛。這些假設忽視了 一個平衡的風險組合的重要效益：在一個領域有安全感，使我們能夠 自由地在另一個領域成為創新者。能夠應付基本的生活開銷，我們就 不會迫於生存壓力而去出版半成熟的書，銷售拙劣的藝術品，或創辦 未經考驗的公司。皮埃爾·奧米迪亞（Pierre Omidyar）創辦億貝 （eBay）時，這只是他的一個興趣；在之後的9個月裡他一直幹著程 序員的工作，直到億貝的收益超過他的薪水時，他才辭去之前的工 作。Endeavor公司創始人兼CEO琳達·羅滕伯格（Linda Rottenberg） 數十年來致力於培訓世界傑出的企業家，她曾說：“最好的企業家並 不是那些追逐最大風險的人，而是努力將風險降到最低的人。” ［18］ 平衡風險組合並不意味著保守持中，不去冒太大風險。相反，成 功的創新者在一個領域冒極大風險，在另一領域卻極度謹慎從而抵消 了風險。薩拉·布雷克裡（Sara Blakely）在27歲時產生一個新穎的想 法——生產無腳連褲襪。當時她只有5000美元的儲蓄，她冒著極大風 險，用所有儲蓄進行投資以實現她的這一想法。為了平衡風險，她繼 續做了兩年銷售傳真機的全職工作，利用晚上和週末時間製作產品原 型。為了節約資金，她親自寫專利申請，而不是僱用律師去寫。當 Spanx內衣公司成功創辦，她成為歷史上最年輕的白手起家的女性億 萬富翁。100年前，當亨利·福特（Henry Ford）開始構建他的汽車帝 國之時，他是愛迪生照明公司的總工程師，這使他有足夠的時間和金 錢做他自己想做的事情——研究汽車。在發明了化油器技術並在一年 後獲得專利權之後，他繼續在愛迪生照明公司工作"
    },
    {
      "title": "2 盲目的發明家與目光狹隘的投資者： 識別原創想法的藝術和科學",
      "page": 13,
      "excerpt": "很多年前，心理學家發現有兩種通往成功的路徑：一種是墨守成 規，一種是創新。墨守成規是指遵循大多數人所走的傳統常規道路並 維持現狀。創新則是指走少數人走過的路，堅信一系列有違常規，但 最終能使事情變得更佳的新想法或價值觀。 當然，沒有任何事物是完全原創的，因為我們所有的想法都受到 我們周圍世界的影響。無論有意還是無意，我們無時無刻不在借用。 我們都受到盜竊癖（kleptomania） ［3］ 的影響，即不經意地記住別 人的想法並把它們當成是自己的。在我看來，創新包括提出並推進一 種想法，這種想法在某一領域中不同尋常，並且有得以改進的潛力。 創新本身始於創造力：想出一個既新穎又實用的概念。但創新又 不止於此。創新者是指那些主動採取行動使他們的想法成為現實的 人。沃比帕克的創建者們擁有創新精神，他們構想出一個不同於傳統 的在線銷售眼鏡的方式。但當他們切實採取行動使眼鏡既能方便購 買，又價廉物美時，他們成了創新者。 這本書要講的是我們可以怎樣更具創新精神。令人意想不到的 是，你選擇哪種網頁瀏覽器竟可以透露出你的創新程度。 打破默認的規則 不久前，經濟學家邁克爾·豪斯曼（Michael Housman）主持了一 個項目，研究為什麼有些客戶服務代表在他們工作崗位上工作的時間 比其他人更久。豪斯曼掌握了3萬餘名員工的數據信息，他們的工作 是處理來自銀行、航空公司和手機公司的呼叫業務。豪斯曼猜測從這 些員工以前的工作經歷中可能會找到一些關於他們工作忠誠度的線 索。他猜測之前有過跳槽歷史的員工會辭職得更快，但事實上他們並 沒有；同過去5年一直做同一份工作的員工相比，在過去5年中做過5 份不同工作的員工辭職的概率並不會更高。 在尋找其他線索的過程中，他注意到了其團隊獲得的關於僱員在 申請工作時使用哪種瀏覽器登錄的信息。一時興起，他測試了關於瀏 覽器的選擇是否與他們辭職有關。他未曾料到會在這兩者間找到任何 相關性，因為我們常常認為選擇用哪種瀏覽器純粹是個人喜好的問 題。但當他看到了結果，他驚呆了：使用Firefox或Chrome瀏覽器的 員工堅守在某一崗位上的時間要比那些使用IE瀏覽器或Safari瀏覽器 的員工長15%。 豪斯曼認為這只是一個巧合，於是又對工作缺勤情況做了相同的 分析。結果竟與之前相同：使用Firefox瀏覽器和Chrome瀏覽器的員 工，其缺勤率比使用IE瀏覽器和Safari瀏覽器的員工要低19%。 然後他觀察了僱員的業績水平。他的研究團隊收集了關於員工在 銷售、客戶滿意度、平均通話時長方面近300萬個數據點。使用 Firefox瀏覽器和Chrome瀏覽器的員工有著明顯更高的銷售額，通話 時間更短。他們的客戶滿意度也更高：使用Firefox瀏覽器和Chrome 瀏覽器的員工在90個工作日內達到的客戶滿意度，需要那些用IE瀏覽 器和Safari瀏覽器的員工花上120個工作日才能達到。 瀏覽器本身並不是造成他們忠於職守、表現踏實並獲得業績成功 的原因。相反，正是他們使用瀏覽器的偏好，釋放出他們有哪些習慣 的信號。為什麼使用Firefox瀏覽器和Chrome瀏覽器的員工在每一個 指標上都更投入，表現更好呢？ 表面上看起來，顯而易見的答案是他們更精通計算機技術。於是 我問豪斯曼他能否對此進行探索。員工們於是全部做了計算機水平測 試，這一測試旨在評估他們在鍵盤快捷鍵、軟件程序和硬件方面的知 識水平，並對他們的打字速度進行了計時測試。但結果是，使用 Firefox瀏覽器和Chrome瀏覽器的員工群體並沒有被證明有更多的計 算機專業知識，他們打字也並不更快或更準"
    },
    {
      "title": "在創意的鋼絲繩上漫步",
      "page": 39,
      "excerpt": "了一半的土豆片重複蘸到醬裡），並說過“not that there’s anything wrong with that”（那沒有什麼不妥之處）這樣的免責聲明，或者拒 絕別人時說了“no soup for you”（沒有你的湯），那麼你正在使用該 劇創造出的短語。但為什麼電視臺主管這麼不看好《宋飛正傳》 （Seinfeld ）呢？ 當我們哀嘆這個世界缺乏創新時，我們把它歸咎於創造力的缺 乏。我們總認為如果人們能產生更多新奇的想法，那麼我們會過得遠 遠好於現在。但現實是，創新精神的最大障礙並不是沒有新想法的產 生，而是沒有對新想法做出正確的選擇。一項調查顯示，當200餘名 被測試者為新公司和新產品想出了超過1000個點子時，其中87%的點 子是完全獨創的。我們的公司、社區和國家從不缺少新奇的想法。它 們缺少的是善於選對創新想法的人。賽格威是個錯誤的樂觀預測：根 據預測，它會帶來轟動，但結果它卻與成功失之交臂。《宋飛正傳》 是個錯誤的悲觀預測：人們預計它會失敗，但最終卻大獲成功。 在這一章中，我想談一談人們在選擇不同想法的過程中會遇到哪 些障礙，以及怎樣做才能選對想法。為弄清我們如何才能減少預測失 誤，我挑選出了一群技藝高超的預言家，他們懂得如何避免錯誤地樂 觀預測和悲觀預測。其中有兩位風險投資家曾預測到賽格威會失敗； 還有一位是美國全國廣播公司（NBC）的主管，他甚至沒有喜劇方面 的工作經驗，但他如此熱衷於《宋飛正傳》的試播集，以至於自己承 擔風險去贊助這部劇的播出。傳統智慧教導我們，在評估一個想法 時，要對比感性直覺和理性分析的相對重要性，並且想法提出者的熱 情程度十分重要，但是這群預言家的做法對傳統智慧提出了質疑。通 過他們的例子，你會明白為什麼主管和參與測試者很難準確地評估新 的想法，以及我們如何才能更好地做出決策。 在創意的鋼絲繩上漫步 賽格威的發明者迪恩·卡門（Dean Kamen）是一位技術高手，他 的衣櫃裡只有一套衣服：牛仔襯衫、牛仔褲和工作靴。當我讓風險投 資家形容一下卡門，他們最常見的回答是“蝙蝠俠”。16歲時，他主動 重新設計了一款博物館照明系統，並說服館長在博物館內進行了安裝 試用。在20世紀70年代，他發明了藥物輸液泵，並因此獲得了一大筆 收入：他買了一臺噴氣式飛機和直升機，在新罕布什爾州建了一幢大 廈，裡面配有一個加工車間、一個電子實驗室和一個棒球場。在20世 紀80年代，他發明的便攜式透析機也獲得了巨大的成功。 在20世紀90年代，卡門設計了iBot，一款可以爬樓梯的輪椅。他 認識到這項技術可以有更廣泛的應用，便召集了一個團隊來幫助創造 賽格威。他的目標是建立一個安全、節能的運載工具，可以避免汙 染，幫助人們在擁堵的城市中行駛。小型、輕便且具有自我平衡能 力，這些特點使得賽格威對於郵遞員、警察和高爾夫球手來說是極好 的裝備。此外，它還有變革當前交通運輸方式的潛力。賽格威是卡門 創造的最非凡的技術作品，卡門預言賽格威“之於轎車，會像當年的 轎車之於馬車一樣”。 但創造者能夠客觀判斷自己的想法嗎？我的學生賈斯汀·伯格如今 已是斯坦福大學的教授，他年輕而才華橫溢，花了許多年來研究這個 問題。伯格擅長創造性預測，這是一門預測新想法未來是否會成功的 藝術。在一項研究中，他向不同人群展示各種馬戲表演的視頻，並讓 他們預測每個表演者的受歡迎程度。包括太陽馬戲團（有加拿大“國 寶”之稱的表演團體）在內的劇團藝術家們也對自己視頻的受歡迎程 度進行了預測。最後，各位馬戲團主管也觀看了視頻，並寫下了預 測。 為了驗證各組被測試者的預測準確性，"
    },
    {
      "title": "親吻青蛙",
      "page": 43,
      "excerpt": "親吻青蛙 如果創新者本人對他們自身想法做出的評判並不可靠，那他們怎 樣才能提高創作出傑作的概率呢？答案是：他們想出大量的創意。西 蒙頓發現，平均而言，創意天才在他們所在領域的作品並不比同行的 作品質量更好，他們只是有大量的想法罷了。這給他們更多的變化， 更高的獲得獨創性的機會。“一個人能想出有影響力的成功創意的概 率，”西蒙頓指出，“同他想出的創意總數成正比。” 想想莎士比亞：我們對他的一小部分經典作品耳熟能詳，但卻忘 記了在20年中，他創作了37部戲劇和154首十四行詩。西蒙頓通過計 算人們多久演一次某部戲劇以及專家和評論家對該劇的好評程度，追 蹤莎士比亞各部戲劇的受歡迎程度。在5年時間裡，莎士比亞創作出 了他最受歡迎的五部作品中的三部：《麥克白》（Macbeth ）、《李 爾王》（King Lear ）和《奧賽羅》（Othello ）。同時他還創作出了 相對一般的作品《雅典的泰門》（Timon of Athens ）和《泰爾親王佩 力克爾斯》（All's Well That Ends Well ），這兩部作品都被認為是莎 翁最糟糕的戲劇，並總是被批評為單調乏味，情節和人物發展不完 整。 縱觀各個領域，即使是最傑出的創造者，通常也有大量作品嚴格 來說是優秀的，但在專家和觀眾看來並不起眼。倫敦愛樂樂團選出的 50部最偉大的古典音樂中，其中有6部是莫扎特的作品，5部是貝多芬 的作品，3部是巴赫的作品。為了創造出大量傑作，莫扎特在他35歲 去世前創作了超過600部作品，貝多芬在一生中創作了650部，巴赫 寫了超過1000部。在對1.5萬部古典音樂作品的研究中，作曲家在任 意5年時間內創作的曲目越多，產生驚世傑作的概率就越大。 畢加索的全部作品包括1800幅油畫、1200件雕塑、2800件瓷 器、1.2萬張圖紙，更不用說大量的版畫、地毯和掛毯了，但其中只 有一小部分贏得了一致好評。在詩歌領域，當我們在背誦瑪雅·安吉羅 （Maya Angelou）的經典詩歌《我仍將奮起》（Still I Rise ）時，我 們往往忘記了她寫的其他165首詩；我們記得她動人的回憶錄《我知 道為什麼籠中的鳥唱歌》（I Know Why the Caged Bird Sings ），但 並不怎麼重視她寫的其他6部自傳。在科學領域，愛因斯坦發表了改 變物理學的廣義相對論和狹義相對論，但在他248部出版物中，許多 作品的影響力很小。 西蒙頓的報告顯示，在各個領域，最多產的人不僅最富有創新精 神，並且他們最具原創力的作品也誕生於他們最多產的人生階段。 7 30至35歲之間，愛迪生髮明瞭電燈泡、留聲機、碳精電話。但在此期 間，他還申請了超過100項其他專利發明，如模具筆、水果保鮮技 術、磁鐵採礦技術，他甚至還設計了一個令人毛骨悚然的會說話的娃 娃。“那些不起眼的發明往往與最重要的作品出現在同一個時期，”西 蒙頓說，“愛迪生儘管擁有1093項專利，但真正最傑出的革命性成就 大概也是屈指可數。” 人們普遍認為，數量和質量二者不可共存，如果你想把工作做得 更好，你必須做得精，但事實證明這是錯誤的。事實上，當涉及想法 的產生，數量是對質量最可預測的因素。斯坦福大學教授羅伯特·薩頓 （Robert Sutton）指出：“創新性思想家會想出很多創意，有些是奇 怪的各種變體，有些是死衚衕，甚至有些是徹底的失敗。但付出這些 代價是值得的，因為他們也同時提出了更多可利用的想法，尤其是創 新性的想法。” ［27］ 很多人無法實現創新，是因為他們只有一些想法，然後就執迷於 將它們煉成完美。在Upworth"
    },
    {
      "title": "原型的囚徒和目光狹隘的偏好",
      "page": 46,
      "excerpt": "夠的反饋，從而無法對最終的產品做出正確選擇。對自己的想法深信 不疑是危險的，不僅因為它會讓我們深受盲目樂觀之苦，還因為它會 阻礙我們獲取必要的多樣性觀點，使我們無法到達創造力的頂峰。 但是，卡門和他的團隊並不是唯一對賽格威過於樂觀的人。史蒂 夫·喬布斯、傑夫·貝索斯、約翰·杜爾，這些大師的判斷又錯在了哪裡 呢？為了找到答案，讓我們先來看看為什麼許多主管和測試觀眾沒有 看到《宋飛正傳》的潛力。 原型的囚徒和目光狹隘的偏好 當第一集《宋飛正傳》的劇本被提交時，主管們不知道該如何處 理。“這是完全非傳統的，”NBC高管沃倫·利特菲爾德（Warren Littlefield）說，“它似乎與電視上播出的其他節目完全不同，沒有任 何先例。” 在賈斯汀·伯格對馬戲團表演的研究中，他發現儘管馬戲團主管比 藝術家預測得更準確，但他們的預測仍然不夠準確，特別是在判斷最 具創意的獨特表演時，主管往往過於規避風險：他們關注的是投資糟 糕想法會付出的代價，而不是嘗試優秀表演可能獲得的收益，這就導 致他們做出大量錯誤的負面預測。為《宋飛正傳》試播集寫初步報告 的人認為，它處於“弱”和“普通”之間。他傾向於給出“普通”的等級， 但他的上司否決了，認為這部劇應該被評為“弱”。 這些錯誤的負面預測在娛樂業十分普遍。工作室高管誤判了很多 大片，例如《星球大戰》（Star Wars ）、《外星人E.T.》（E.T. ）、 《低俗小說》（Pulp Fiction ）。在出版業，出版商曾拒絕過《納尼亞 傳奇》（The Chronicles of Narnia ）、《安妮日記》（The Diary of Anne Frank ）、《飄》（Gone with the Wind ）、《蠅王》（The Lord of the Flies ）和《哈利·波特》（Harry Potter ）。截至2015年， 僅J.K.羅琳（J.K.Rowling）一人的書就帶來了250億美元的收入，超 過愛沙尼亞整個國家的GDP。而在企業創新的史冊中，許多主管都曾 要求其員工停止那些最終引發了巨大轟動的項目，例如日亞公司 （Nichia）的LED燈、龐蒂亞克（Pontiac）的Fiero車、惠普的靜電顯 示器；家用電視遊戲機Xbox險些被埋沒在微軟；複印技術的發明者施 樂公司（Xerox）也差點因為昂貴和不實際而取消了激光打印機的發 明。 當我們面對不確定性時，我們的第一反應往往是拒絕創新 ［28］ ，傾向於認為不熟悉的概念會招致失敗。當管理者仔細檢測新奇的想 法時，他們抱著評價的心態。為了保護自己免受糟糕預測帶來的風 險，他們將新概念放上臺面，同過去已經獲得成功的想法進行比較。 當出版集團的高管對《哈利·波特》進行評估時，他們認為作為一本兒 童讀物，這本書的篇幅過長；當NBC負責人布蘭登·塔迪考夫看到了 《宋飛正傳》的試播集時，他認為這部劇“太猶太人化”和“太紐約 化”，不能吸引廣泛的觀眾群體。 萊斯大學教授埃裡克·戴恩（Erik Dane）認為，人們獲得越多的 專業知識和經驗，他們觀察世界所用的某種方式就變得越發根深蒂 固。 ［29］ 他指出，研究顯示，當橋牌規則被改成由擁有最小牌的玩 家先出牌，而不是擁有最大牌的玩家先出牌，專業的橋牌選手表現得 比新手更難適應；在使用取消了舊規定的新稅法時，專業會計師比新 手做得更糟糕。隨著我們對某一領域的知識增多，我們也成了自己頭 腦中原型的囚徒。 理論上來說，觀眾對於創新理應比主管的心態更加開放。他們不 受專業知識的束縛，而且在考慮新形式、對不同尋常的想法表達熱情 時也不"
    },
    {
      "title": "經驗是一把雙刃劍",
      "page": 50,
      "excerpt": "想出一些創新想法。僅僅6分鐘的創新性思考就能使他們更容易接受 創新，從而讓他們提升更能發現不尋常事物的潛力。 從這些發現中，你可能會得出結論，認為只要確保主管有一些創 造者那樣的經驗，我們就可以提高主管對創新想法的選擇能力。但從 伯格馬戲團實驗得出的數據來看，之前有過藝術家經歷的主管並不比 普通的主管做出的評價更準確；純粹的藝術家仍然是最好的預測者。 一旦你擔任了管理者的角色，你就很難避免評價性心態，從而做出錯 誤的負面預測。伯格在一項實驗中證明了這一點。他要求被測試者先 想出一些產品創意，然後再列出評判標準，接著他讓實際用戶來衡量 這些創意成功與否。先像創造者一樣思考，然後再扮演管理者的方式 使被測試者的預測準確度降低至41%。當伯格顛倒順序，讓他們先扮 演管理者，再像創造者一樣思考，他們的正確率就上升到了65%。如 果我們想要提高成功預測創新性想法的準確度，我們必須在審視他人 的想法之前自己先想出一些創意。而這一點，恰恰能夠解釋為什麼 《宋飛正傳》最後會大獲成功。 經驗是一把雙刃劍 當測試觀眾對《宋飛正傳》的試播集表達了嚴厲批評時，“這像 是往胸口捅了一刀，”沃倫·利特菲爾德回憶道，“由於調查反映出觀眾 的強烈反對，我們不敢貿然前進。”雖然喜劇劇作家是決定這部劇生 死的最理想群體，但當時並沒有一個純粹的劇作家掌握著這樣的權 力。但瑞克·路德溫（Rick Ludwin），這個最終使節目得以播出的 人，可以說是繼劇作家之後的最佳人選。 路德溫之後還做了很多出名的事情。 8 ，也曾為科南·奧布萊恩 （Conan O’Brien） 9 出面，續訂了之前並沒有多少收視率的美劇 《辦公室》（The Office ）。但他對電視產業的最大貢獻還在於資助 了《宋飛正傳》的播出。 那時，瑞克·路德溫甚至沒有在喜劇部門工作過，而是正在處理專 輯節目。由於《宋飛正傳》試播集沒有取得成功，他肩負了再給它一 次機會的使命。他從節目時間表中找出了幾小時的空當，把劇本分成 半小時的節目，還從特別預算中拿出一部分錢來投資更多劇集的播 放。“據我所知，這是有電視節目以來最小的訂單。”路德溫說。用傑 裡·宋飛（Jerry Seinfeld）後來的話說，六集的訂購“就像一記耳光”， 而NBC只訂購了四集。 早在1982年，史蒂夫·喬布斯就說過：“如果你想進行創新性的聯 想 ［30］ ，你要有同他人不一樣的經歷。”沒有情景喜劇部門的工作經 歷可能是瑞克·路德溫最大的優勢。“拉里和傑裡從來沒有寫過一部情 景喜劇，而我工作的部門也沒有製作過，”路德溫回憶道，“我們是一 對很好的搭檔，因為我們不知道哪些規則不應該打破。”他的局外人 身份使他能夠不被情景喜劇的標準模式所限制，從而能夠去考慮一些 不同的東西。大多數情景喜劇都是在22分鐘一集的時間內拍攝幾幕連 續的場景；而《宋飛正傳》則常常留下懸而未決的衝突，並有多達20 個不同的場景集中在一集內。如果你只有拍攝情景喜劇的經驗，那麼 這種拍攝方式無疑很讓人困擾，但對於一個在每一集都想做出不同安 排的人來說，這種方式似乎並沒有什麼不妥。 與此同時，路德溫又的確有創作喜劇所需要的經驗。在20世紀70 年代，身為製片人的他曾寫過段子並將它們賣給了著名喜劇演員鮑勃· 霍普（Bob Hope），接著他還製作了一個白天檔的綜藝節目，內容是 喜劇小品片段。“被喜劇作家們包圍就像是去參加一個棒球夢幻訓練 營。你覺得你真的很不錯，直到你拿起球拍開打，”他回憶道，“你不 僅不能擊到球，你甚至連球都看不到。我知道我和他們不是一個檔次 的，但我至少和他們有共同語言。"
    },
    {
      "title": "直覺的偶然性，又或者說史蒂夫·喬布斯錯在哪裡",
      "page": 55,
      "excerpt": "性產品的設計師曾在兩個或三個不同的國家工作過。 其次，外國文化與本土文化的差異性越大，越有助於激發設計師 的創造力。一個美國人在韓國或日本工作獲得的創造性經驗會比其在 加拿大工作獲得的創造性經驗要多。 但是，僅在多個國家、在不同的文化背景下工作是不夠的。第三 個也是最重要的因素是深度——在國外工作的時間長短。短期的工作 不會有太大幫助，因為設計師沒有足夠長的時間去吸收從外來文化中 獲得的新想法，並將這些新想法同他們舊有的觀點相結合。當設計師 在國外有35年的工作經驗時，他們的創造力剛好可以達到頂峰。 瑞克·路德溫的經歷就與這種模式相契合。他在不同喜劇作品上有 十多年的工作經歷，這使他的經驗有一定的深度。他在電視製作方面 的經驗很廣，這就好像他在幾個不同的國家生活過一樣：他做過綜藝 節目和特別專題節目，也做過白天檔和深夜檔的脫口秀。他諳熟於多 種電視語言，因此在其他人產生懷疑的地方看到了希望。在他使《宋 飛正傳》獲得批准之後，路德溫繼續負責這部劇的每一季，他看好那 些和他一樣有著內外部經歷的作家。《宋飛正傳》的大部分編劇都來 自深夜檔節目，在《宋飛正傳》之前，大多數人從來沒有參與過情景 喜劇的創作，這意味著“他們不會存在沒有創新想法的問題” 10 直覺的偶然性，又或者說史蒂夫·喬布斯錯在哪裡 史蒂夫·喬布斯第一次踩上賽格威就不願下來。當迪恩·卡門轉向 其他潛在投資者時，喬布斯勉強拱手讓人，但很快又插手干涉。喬布 斯邀請卡門共進晚餐，如同記者史蒂夫·肯佩爾（Steve Kemper）所 說，喬布斯“認為這個機器同迷人的個人計算機一樣具有創新性，他 認為他必須要參與”。 史蒂夫·喬布斯以憑藉直覺下賭注而不是系統分析而聞名。為什麼 他在軟件和硬件上的預測是準確的，而這次卻失誤了？三股強大的力 量使他對賽格威的潛力過於自信：對相關領域的經驗缺乏、傲慢和熱 情。 讓我們先從經驗談起。許多NBC的高管對傳統情景喜劇有太多經 驗以至於無法欣賞《宋飛正傳》的不同尋常之處，然而賽格威的早期 投資者存在相反的問題：他們在交通運輸方面缺乏經驗。喬布斯的專 長在數字世界，傑夫·貝索斯是互聯網零售業之王，約翰·杜爾的大部 分財富來自於對軟件和互聯網公司的投資，例如太陽微系統公司 （Sun Microsystems）、網景（Netscape）、亞馬遜和谷歌。他們都 是各自領域的創新者，但在一個特定領域成為創造者並不會使你成為 另一領域的偉大預測者。為準確預測一個新想法獲得成功的概率，你 最好先成為該領域中的創造者。 埃裡克·戴恩帶隊進行的一項新研究向我們展示了其中的原因：我 們的直覺只有在我們擁有很多經驗的領域才會準確。 ［32］ 在這項實 驗中，他讓人們觀察十隻名牌手袋，判斷哪些是正品哪些是仿製品。 一半的參與者只有5秒鐘時間進行猜測，這迫使他們不得不依靠自己 的直覺。另外一半參與者有30秒時間，這讓他們可以檢查和分析手袋 的特徵。戴恩的研究小組還測量了參與者對手袋的經驗：有些人有很 豐富的經驗，擁有3只以上的蔻馳（coach）或路易威登（Louis Vuitton）的手袋，而其他人從未接觸過名牌手袋。 如果你本身就擁有好幾只大牌手袋，那麼你檢查它們的時間越 短，你的判斷就越準確。對於那些有名牌手袋購買經驗的被試者來 說，他們在5秒內做出的判斷要比他們在30秒內做出的判斷準確率高 出22%。當你對手袋有多年的研究，你的直覺就會比分析更準確，因 為你的潛意識擅長模式識別。 11 這時候，如果你停下來去思考，反 倒會只見樹木、不見森林。 但如果你對手袋一無所知，那麼直覺對你不會"
    },
    {
      "title": "激情的風險",
      "page": 59,
      "excerpt": "靠，我們越來越需要對分析給予重視。 鑑於喬布斯在交通運輸方面並沒有多少經驗，他為什麼如此相信 自己的直覺呢？這就要談到我先前提到的第二個因素了。“驕傲會伴 隨著成功而來。”科密薩爾解釋說，“如果我當時重申我的疑慮，喬布 斯可能會說‘你不懂。你太傻了’。”科密薩爾對於交通和航空業的研究 佐證了他的觀點：過去越成功的人，在新環境中的表現越差。他們過 於自信，而且不太可能會聽取別人的批評意見，即使他工作的新環境 與之前是完全不同的。喬布斯就陷入這類成功陷阱：由於之前他的經 歷證明了反對者的想法是錯誤的，他覺得沒必要聽取相關領域的創造 者提出的意見，他不需要用他們的觀點來驗證其直覺是否正確。當他 遇到迪恩·卡門熱情澎湃的產品展示時，直覺使他進一步誤入歧途。 激情的風險 當卡門推銷賽格威時，他滿懷激情地談到中國和印度等發展中國 家的現狀，它們每年都在建造像紐約這樣大規模的城市。這些城市中 心將出現汽車擁堵，這不利於環境保護；而賽格威可以解決這個問 題。“卡門代表著大自然，”艾琳·李回憶道，“在環保方面，他掌握專 業的技術，擁有豐富的經驗，並充滿激情，所以我們都被他打動 了。” 美國東北大學（Northeastern University）創業學教授謝麗爾·米 特尼斯（Cheryl Mitteness）帶頭做了一項研究，超過60位天使投資 人對企業的宣傳做了3500多份評估，並決定是否會給它們提供資金。 接著研究人員讓投資人填寫了一份調查表，以觀察他們的決策風格是 更偏直覺還是更靠分析。然後，他們對每個企業家的熱情和積極性進 行了排名，並評估了每個初創企業獲得資金的潛力。結果顯示，越是 憑直覺進行判斷的投資人，越容易受到企業家熱情的影響。 正如丹尼爾·卡尼曼在《思考，快與慢》（Thinking， Fast and Slow ）中的解釋：直覺是基於我們熱切的情感而迅速行動，而理智是 更緩慢、冷靜的過程。直覺型的投資人很容易陷入企業家的熱情當 中；分析型投資人則更可能把重點放在事實上，對業務的可行性做冷 靜的判斷。喬布斯的直覺風格使他更容易被卡門的激情和技術本身的 創新力所影響。他的傲慢和缺乏交通運輸的經驗使他容易相信最終被 證明是錯誤的樂觀預測。 當評估一個新想法的前景時，我們很容易被想法提出者的熱情所 吸引。用谷歌高管埃裡克·施密特（Eric Schmidt）和喬納森·羅森伯格 （Jonathan Rosenberg）的話來說：“熱情的人並不把他們的激情放 在袖子裡，他們把它藏在心裡。” ［33］ 我們難以從人們的情感表達中 切實看到那種希望想法變為現實的熱情。人們從話語、語氣、肢體語 言中展現出來的熱情並不能成為判斷其內在熱情的線索，只能被視為 是演說技巧和性格的反應。例如，研究表明，外向的人往往比內向的 人更富有表現力，這意味著外向的人能夠表現出更多的激情。但是， 我們外向與否從本質上說與我們是否會成為成功的企業家並沒有關 係。你可以鍾愛一個想法，下定決心要獲得成功，但仍然可以用一種 保守的方式表達出來。 這並不是說，激情與企業成功無關。有大量證據表明，富有激情 的企業家能夠使企業成長得更快更成功。對卡門而言，他缺乏能夠幫 助他將想法從發明轉變為實際影響力的熱情。早期投資者們不應該被 卡門創造賽格威的激情所吸引，而應該對卡門對於建設公司，使產品 成功推向市場的激情進行評估。要做到這一點，他們不應該把注意力 放在他所說的話上，而是應該研究他所做的事情。 研究卡門的歷史後，蘭迪·科密薩爾得出結論，卡門是一位更令人 印象深刻的發明者，但不是企業家。過去，卡門那"
    },
    {
      "title": "如何儘可能地選對創意",
      "page": 61,
      "excerpt": "解決方案，但卻不擅長自己找到對的問題去鑽研。以賽格威為例，他 先想出了一個解決方案，然後再去尋找問題。他並不是應市場的需求 去發明一種產品，而是自己創造了一個錯誤的產品，然後去尋找市 場。 雖然卡門對賽格威充滿激情，但他沒有準備好成功地執行賽格威 的方案。如果想提高對想法進行選擇的能力，我們不應該只看到人們 是否曾經獲得過成功。我們需要跟蹤他們是如何取得成功的。“當我 們觀察卡門，我們看到的是一個偉大的創始人，他發明的醫療設備獲 得很多成就，而與他一起發明這些產品的人仍舊追隨著他，”艾琳·李 說，“而論及產品研發，每一天的執行力和保證產品擁有高性價比是 很重要的。”卡門沒有這種經驗。比爾·薩爾曼補充說：“重要的從來不 是想法，而是執行。” 要預測一個創新想法的創造者是否會獲得成功，我們不能只看他 們在表達想法時的激情，還應該關注他們在執行力上的激情。瑞克·路 德溫看好傑裡·宋飛和拉里·戴維（Lany David），並不是因為他們在 介紹自己的劇本時看起來充滿激情。之所以給了他們一個機會，是因 為他看到他們認真地修改自己的想法，並觀察到他們有能力把事情往 正確的方向推動。“他們倆會在第二天演出前在工作室待到半夜，努 力對第二幕進行修改。你會看到傑裡在工作中非常仔細。這就是你要 找的激情。” 如何儘可能地選對創意 沒有投資沃比帕克是我犯下的一個嚴重的負面預測反例。在閱讀 了關於想法選擇的研究後，我很快意識到了我的侷限之一：我既不是 這一領域中的創造者，也不是客戶。起初，我將我預測的失敗歸結為 我滿分的視力。如果你從沒戴過眼鏡，你就難以判斷顧客的喜好。但 反思後我意識到，我真正缺乏的是深入瞭解。我曾花了兩年時間為一 家眼睛保健公司做研究和諮詢，這家公司的主要收入來源是銷售眼 鏡，驗光師提供給病人處方，然後病人進行試戴。我陷入了傳統的眼 鏡買賣模式中。如果我在聽到沃比帕克的公司宣傳前花一點時間自己 想出一些創意，或者瀏覽一下其他服裝和配飾產品的網絡銷售模式， 我也許會對沃比帕克的想法持更加開放的態度。 這四個創始人並沒有受到這些傳統思維的妨礙：他們有深刻的認 識和廣泛的經驗。他們中有三個人佩戴眼鏡，並且可以把各自在生物 工程、醫療、諮詢以及銀行業方面的經驗結合在一起。身為創始人之 一的戴夫，曾有好幾個月時間在國外旅遊，在這期間，他不僅沒帶手 機，而且丟失了眼鏡。當他回到美國，他需要同時買一部手機和一副 眼鏡，這讓他對於購買眼鏡的方式產生了新的想法。尼爾·布盧門撒爾 不戴眼鏡，但他曾在過去5年裡為一家非營利機構工作，負責培訓亞 洲、非洲和拉丁美洲的女性創業者。他教婦女銷售的產品正是眼鏡， 這使他對眼鏡業有了一定深度的瞭解：他知道眼鏡完全可以以更低的 價格製作、設計並出售。 在非傳統眼鏡銷售渠道的工作經歷使他能夠採取一種新的銷售眼 鏡的方式。“創新很少來自內行，”尼爾告訴我，“尤其是當他們在眼鏡 行業中擁有穩固地位，高枕無憂時。” 擁有多領域的經驗使得沃比帕克的創始人們不受現有原型的阻礙 或評價性心態的限制。與卡門充滿激情的銷售模式相反，他們沒有假 設他們的想法會行得通，他們首先大量尋求來自同行創造者和潛在客 戶的反饋。由於去掉了中間零售商，他們可以將通常要賣500美元的 眼鏡以45美元售出。一位營銷專家對此提出了忠告，告訴他們這樣的 做法會使成本增加，而且價格被顧客視為質量的標誌，價格太低也會 帶來負面影響。接受這一忠告之後，他們投放出一批模型產品進行調 查，隨機分配給客戶不同的價格。他們發現，當價格在100美元左右 時，購買的可能性達到峰值，隨著價位升高"
    },
    {
      "title": "3 孤立無援：向上級說出真實想法",
      "page": 20,
      "excerpt": "Sternberg）所言：“一旦人們為了獲得成就而屈居於中間水平，有證 據表明，實際上他們的創造力在降低。” 期望獲得成功的渴望和害怕失敗的恐懼阻礙了歷史上一些最偉大 的創造者和變革推動者。他們關心如何保持穩定和實現傳統意義上的 成就，因而一直不願意追求離經叛道。他們沒有充滿信念地孤注一 擲，而是被哄著，被說服，或被脅迫保持不動。雖然他們似乎擁有成 為一個天生領導者的素質，但形象地說，有時甚至是毫不誇張地說， 他們是被追隨者和同行抬起的。如果當初為數不多的那幾個人沒有聽 從他們內心的反叛直覺，美國或許根本不存在，民權運動可能還只是 個夢，西斯廷教堂可能是光禿禿的，我們大概還堅信著太陽是繞著地 球轉的，個人電腦可能永遠不會得到普及。 現在看來，《獨立宣言》似乎是不可避免的 ［8］ ，但當時由於 幾位關鍵性革命人物的不情願，它差點沒有誕生。“那些在美國獨立 戰爭中擔當指揮角色的人物，和大家想象中的革命者形象相去甚 遠，”歷史學家兼普利策獎得主傑克·雷科夫（Jack Rakove）敘述 道，“儘管他們本身不想成為革命者，但最終還是成為了革命者。”在 戰爭前夕的那幾年，約翰·亞當斯（John Adams）害怕英國會報復， 猶豫著是否要放棄自己剛剛起步的律師生涯，直到當選為代表，出席 第一屆大陸會議之後，他才參與進來。喬治·華盛頓（George Washington）一直專注於管理其遺產以及小麥、麵粉、漁業和養馬的 生意，直到亞當斯任命他為軍隊總指揮後，他才加入革命事業。華盛 頓曾說，“我已經用盡我所有力量去避免它”。 近兩個世紀後，馬丁·路德·金對於領導民權運動感到擔憂，他那 時的夢想是成為一名牧師，併成為大學校長。1955年，在羅莎·帕克 斯（Rosa Parks）因為搭乘公交車時拒絕讓座給白人而被逮捕後，一 群民權活動家聚集在一起，討論他們應該如何回應。他們同意組建蒙 哥馬利進步協會（Montgomery Improvement Association）以發起抵 制公交車運動，與會者之一提名了馬丁·路德·金做主席。金回憶 道：“此事發生得如此之快，以至於我還沒有時間去深入思考它。如 果我有時間的話，我會拒絕這項提名。”就在三週前，金和他的妻子 達成一致，“之後不會再承擔任何重大社會團體的工作，因為我最近 剛完成我的論文，需要更多精力投入教會工作”。然而他被一致推選 為這場運動的領袖。那天晚上，他要面向社會發表演說前，他 說：“我充滿恐懼。”1963年，他的講話獲得雷鳴般的掌聲，鼓舞了全 國各地追求實現自由理想的人們，之後，金才克服了恐懼。之所以做 這次演說，只是因為有一位同事提出，金應該在3月華盛頓大遊行的 閉幕式上發表演講，並召集一群領袖給他支持。 當教皇委派米開朗琪羅在西斯廷教堂的天花板上畫壁畫時，後者 並沒有什麼興趣。他認為自己是一個雕塑家，而不是畫家，他發現任 務十分艱鉅，因而逃到了佛羅倫薩。在教皇的堅持下，兩年後他才接 受這一任務。由於哥白尼拒絕發表他的日心說理論，天文學停滯了幾 十年——由於擔心排斥和嘲笑，哥白尼保持了22年的沉默，他的發現 只在他的朋友中流傳。最終，一位紅衣主教得知了他的研究，並寫了 一封信鼓勵哥白尼將其理論出版。即使這樣，哥白尼還是拖了4年才 行動。在一位年輕的數學教授主動承擔這個任務，把書付梓之後，他 的鉅著才為世人所知。 近500年之後的1977年，在天使投資人決定拿出25萬美元投資史 蒂夫·喬布斯和史蒂夫·沃茲尼亞克的蘋果公司時，他發出了最後通 牒：沃茲尼亞克必須離開惠普。沃茲尼亞克拒絕了。“我還是準備長 久在惠"
    },
    {
      "title": "沒有地位的權力",
      "page": 69,
      "excerpt": "有意義的政策，倡導一種創新的辦事方式，或者支持一個弱勢群體。 在這一章中，我將談到應該何時發表意見，以及如何在不危害我們的 事業和人際關係的情況下有效地做到這一點。什麼時候是發表意見的 恰當時機？我們可以採取哪些步驟才能獲得傾聽？隨著我們敘述卡門· 梅迪納的故事，你將從一個反向推銷自己公司的企業家以及一個挑戰 史蒂夫·喬布斯的公司主管身上學到一些道理。你會明白為什麼最支持 你的管理者有時能給你的幫助卻是最少的，性別和種族如何影響我們 意見的發表，以及為什麼我們在評判自己的照片和別人的照片時，標 準有差異。我的目標是說明我們如何減少發表意見的風險，並獲得發 表意見的潛在好處。 沒有地位的權力 雖然員工主動提供幫助、建立網絡、收集新的知識並尋求反饋會 得到領導者和管理者的欣賞，但有一種形式的主動倡議會遭到批評 ［35］ ：發表觀點。一項覆蓋製造業、服務業、零售業和非營利機構 的研究發現，向上級發表意見越頻繁的員工，他們在兩年時間內獲得 加薪和晉升的概率就越小。在一項實驗中，當個人表達了他們對種族 主義的反對，那些沒有發表反對意見的人會批評他們是偽善的人。當 我們在道德梯子上爬得越高，我們會越感孤單，高處不勝寒。 要了解卡門·梅迪納遇到的障礙，我們需要梳理出往往會混為一談 的社會等級的兩個主要維度：權力和地位。權力涉及對他人施加控制 或權威，地位則是受到尊重和欽佩。在一項由北卡羅來納大學的教授 艾莉森·法拉格（Alison Fragale）領導的實驗中發現，人在沒有地位 的情況下行使權力會受到懲罰。當人在缺乏尊重時試圖施加影響時， 別人會認為此人是難以相處、強硬、自私自利的。因為此人還沒有贏 得別人的欽佩，因此我們覺得他無權告訴我們該怎麼做，並反對他的 想法。這正是發生在卡門·梅迪納身上的：她多年的海外工作經歷使她 在局內沒有多少地位，她還沒有機會向同事證明自己的價值，所以他 們對她的想法沒有任何信任。由於人們輕視她的意見，她愈加沮喪。 當我們試圖去影響他人，卻發現他們不尊重我們時，這會激起憤 恨，形成惡性循環。為強調我們自己的權威，我們的反應是訴諸越來 越無禮的行為。這種惡性循環的最令人震驚的示範，是這樣一個實 驗：研究人員讓兩人一對一起完成任務，其中一人擁有指派任務的權 力，對方完成這指派的任務可得到50美元的獎金。當隨機抽出的掌權 者得知他們的同伴欽佩和尊敬他們時，他們選擇了最合理的任務：為 獲得50美元的獎金，他們的同伴要講一個有趣的笑話，或寫自己前一 天的經歷。但是，當掌權者得知他們的同伴看不起他們，他們會選擇 一些丟人的任務來報復，比如讓他們的同伴學三聲狗叫，說五次“我 是卑鄙下流的”，或者從500開始報出每減去7得到的結果。僅僅是被 告知另一方不尊重他們，就使他們利用手中的權力貶損對方的概率增 加了近一倍。 卡門·梅迪納還沒達到這種程度。但當她繼續發表意見，她在沒有 地位的情況下努力行使權力的做法就引起越來越多的負面回應。地位 不是要求別人給予的，而是必須靠自己贏得的。 多年後，在她第二次的努力過程中，梅迪納不再嘗試從下層攻擊 體制，從而避免犧牲自己工作的風險。她的目標是通過成為體制的一 部分來贏得地位，然後試圖從內部進行改變。正如著名導演弗朗西斯· 福特·科波拉（Francis Ford Coppola）所說：“獲得權力的方式並不總 是僅僅去挑戰已有權力，而是首先在其中獲得地位，然後再挑戰已有 權力。”梅迪納冒險選擇再次提出她的想法前，她申請了一份關注信 息安全的工作來平衡風險組合，她的主要職責是確保信息安全。“這 不是我通常願意做的工"
    },
    {
      "title": "邁出最差的一步：賽瑞克效應（The Sarick Effect）",
      "page": 72,
      "excerpt": "的行動提供了最需要的支持，使他們得以在保密的文化環境中引入開 放資源的理念。 梅迪納已經擁有了權威，因此她不必再顧慮提出異議的方式。但 是一路走來，為了贏得地位，並最終獲得權威，她的確需要改變與人 交流的方式。她的策略轉變與下面的故事有異曲同工之妙，這大概是 你遇見過最奇怪的創業公司。 邁出最差的一步：賽瑞克效應（The Sarick Effect） 魯弗斯·格里斯科姆（Rufus Griscom）和阿莉莎·沃克曼（Alisa Volkman）有了第一個孩子後，由於看到社會上存在大量誤導性的育 兒廣告和糟糕建議而感到十分震驚。他們創辦了一個叫作Babble的在 線雜誌和博客來挑戰主流的關於育兒的陳詞濫調，並用幽默來應對冷 酷的真相。2009年，當格里斯科姆向風險投資者宣傳Babble時，他做 的與每個創業者的慣例完全相反：他展示了一個幻燈片，列出不對他 的業務進行投資的五項理由。 這種做法本應該是對他的宣傳的致命打擊。投資者希望找到讓他 們進行投資的理由，而在他這裡，他列出的是不讓他們進行投資的理 由。企業家應該說自己公司的優點，而不是缺點。但他這種有違常識 的做法奏效了：那年，Babble獲得了330萬美元的投資。 兩年後，格里斯科姆去迪士尼進行推銷，看他們是否有興趣收購 Babble。這個推銷在邏輯上是不可想象的——他一開始就介紹了缺 點。承認你的初創企業存在問題並承諾會加以改進是一回事，但當你 要銷售一個已經成立的公司時，你有充分的理由去強調其優勢，而不 是一直停在談論公司的不足之處上。 但奇怪的是，格里斯科姆居然再次成功了。他有一張幻燈片上寫 道：“這就是你不應該收購Babble的原因。” 向迪士尼數字家庭部門展示時，他解釋說：用戶每次訪問不到三 個頁面，用戶參與度低於預期；Babble應該是一個育兒網站，但40% 的帖子是關於名人的；網站的後端程序亟須再次調整。 迪士尼最終以4000萬美元的價格購買該公司。 這就是所謂的賽瑞克（Sarick）效應，它以社會科學家萊斯利·賽 瑞克（Leslie Sarick）命名。 在以上兩種情況下，格里斯科姆表達意見的對象比他擁有更多的 權力，而且他還要試圖說服他們提供他們的資源。我們大多數人認 為，要想有說服力，我們應該強調我們的優勢，儘量減少我們的弱 點。的確，在我們的聽眾持支持態度的情況下，這種強大的溝通方式 是有意義的。 但當你是在推銷一個新的想法或一個帶來變革的建議時，你的聽 眾很可能是持懷疑態度的。投資者從你的論點中尋找漏洞，主管們尋 找你的建議行不通的理由。在這種情況下，至少有四方面的原因可以 說明，採用格里斯科姆強調想法中缺點的軟弱溝通方式其實更有效。 第一個優勢是，首先強調自己的弱點可以打消聽眾的疑慮。營銷 學教授瑪麗安·弗里斯泰德（Marian Friestad）和彼得·懷特（Peter Wright）發現，當我們意識到有人試圖說服我們，我們會自然而然地 提高心理上的防禦。過度氾濫的信心像一面紅旗，給我們發出警告， 告訴我們要防止別人對我們帶來的影響。在Babble早期，格里斯科姆 曾在頭兩次董事會會議的展示中談到了公司的一切優勢，希望能讓董 事對公司的發展勢頭和潛力充滿熱情。“每當我強調公司的優勢所 在，我就會得到董事懷疑的態度，” ［37］ 他回憶說，“無限樂觀這種 推銷手段看起來有點不誠實，因此受到質疑。每個人都會對這種推銷 感到反感，或產生懷疑。” 在董事會的第三次會議上，格里斯科姆改變了他的做法，首先開 誠佈公地討論公司存在的所有問題以及讓他徹夜難眠的擔憂。雖然這 種策略在"
    },
    {
      "title": "陌生產生輕視",
      "page": 77,
      "excerpt": "易想到的事物，我們就越會認為它常見和重要。讓高管想出生活中3 件幸福的事情對他們來說是輕而易舉的事，他們立即列出他們對孩子 和配偶的愛以及他們對工作的熱愛。由於列舉兩三條生活中的樂事非 常容易，他們由此推斷，他們的生活是相當幸福的。但是很顯然，要 列舉生活中12件幸福的事並不那麼容易。他們寫了家庭和工作之後， 高管們通常會提到他們的朋友，然後詢問他們能不能把朋友一個個單 獨計算。他們費了很大力氣才寫出他們生活中12件幸福的事情，並由 此得出結論，認為他們的生活並不那麼好。 14 這正是投資者們在魯弗斯·格里斯科姆指出Babble的弱點時所想 的。格里斯科姆承認了Babble最嚴重的一些問題，這就使得投資者們 很難再想到公司存在的其他問題。當他們自己努力地去尋找Babble的 其他問題時，就會認為Babble的問題實際上並沒有那麼嚴重。當格里 斯科姆在Babble早期的董事會會議中測試他的顛倒宣傳策略時，他就 發現了這一點：“當我一開始列出可能會對公司不利的因素時，董事 會的反應卻是完全相反的——哦，這些東西並不那麼糟。牛頓第三定 律可以適用於人類動力學之中——每一個行為都有一個大小相等、方 向相反的反作用力。” 正如展示自己的弱點反而可以使聽眾更難想到其他的弱點，能否 有效表達，取決於我們是否能讓想法的積極一面更容易被聽眾所理 解。而這一點又取決於是否能讓聽眾對你所要表達的信息感到更加熟 悉。 陌生產生輕視 請看以下列出的一些熟悉的歌曲。選擇其中一曲，並在桌上敲出 它的旋律： ● 《生日快樂歌》 ● 《瑪麗有隻小綿羊》 ● 《鈴兒響叮噹》 ● 《晝夜搖滾》 ● 《一閃一閃亮晶晶》 ● 《划船歌》 ● 《星條旗之歌》（美國國歌） 現在，你認為你的朋友能夠聽出你所敲旋律的歌曲的概率有多 大？ 多年來，我一直在讓領導者和學生做這一練習，在派對上做這個 練習十分有趣，又有教育意義。你預計結果如何？如果說概率為零， 你要麼是質疑自己的敲擊技能，要麼是嚴重懷疑你朋友的聽力。在斯 坦福大學最初的研究中，敲擊的人認為聽眾很容易能猜到是什麼歌 曲，他們預測同伴會有50%的概率正確說出歌曲的名字。但當他們真 正敲擊歌曲旋律時，猜對的概率只有2.5%。在敲擊的120首歌曲中， 人們預計會有60首歌曲被猜對。而在現實中，只有3首被猜對。在眾 多機構中我發現了相同的結果。在摩根大通的高層領導團隊會議上， 首席執行官傑米·戴蒙（Jamie Dimon）預測，坐在他旁邊的高管 100%會猜對。他碰巧猜對了。但大多數的時候，我們對自己的預測 過於自信。這是為什麼呢？ 對於正常人來說，在頭腦中沒有聽到歌曲曲調的情況下，是不可 能敲擊出一首歌的旋律的。因此我們無法想象，當你的聽眾在沒有聽 到伴隨的曲調的情況下，你敲出的斷斷續續的聲音對他們來說意味著 什麼。正如奇普·希斯（Chip Heath）和丹·希斯（Dan Heath）在《粘 住》（Made to Stick ）中寫道：“聽眾無法聽到那個曲調，他們所能 聽到的只是一堆斷斷續續的敲擊聲，就像是一種奇怪的莫爾斯電 碼。” 這就是說出創新想法時所面對的一個核心挑戰。當你提出一個新 的建議，你不僅在你的腦中聽到一個曲調。"
    },
    {
      "title": "在離開之前放棄",
      "page": 81,
      "excerpt": "後在週末尋求反饋。 當卡門·梅迪納在2005年成為中情局情報副主管，她明白如果她 想讓情報分析師更加公開地分享信息，就必須經常向他們灌輸她的想 法。於是，她開通了一個保密的內部網絡博客，這一模式與她所推崇 的透明模式非常相像。她每週寫兩次簡短的評論，表達她的觀點，即 需要更少的保密，更多的信息共享，並暗示這將是未來的發展趨勢。 起初，許多領導者本能地駁回了這一想法。但正如關於接觸的研究顯 示，在其他對話之間穿插著簡短的陳述，以及中間的延遲，使領導者 重溫梅迪納的想法。不久，中情局的技術專家在內部網絡開發一個平 臺，允許員工建立自己的博客——熟悉度進一步蔓延。人們開始讚揚 梅迪納開通博客的勇氣 15 。如今，多虧了她的努力，情報界擁有了 一個充滿活力的博客，不同機構的分析師可以在其中用非正式的方式 分享知識。 在離開之前放棄 當我得知卡門·梅迪納的故事，我實在不明白為什麼她因為發表自 己想法毀了自己的職業生涯後還是繼續選擇發表自己的想法。據經濟 學家阿爾伯特·赫希曼（Albert Hirschman）的一本經典著作介紹，應 對不如人意的處境有四種不同的選擇。幾十年的研究表明，無論你對 自己的工作、婚姻或者政府滿不滿意，你的選擇不外乎退出、發出聲 音、保持忠誠和忽視這四種。退出意味著從這一處境中完全脫身：放 棄一份痛苦的工作，結束一段恥辱的婚姻，或離開備受壓抑的國家。 發出聲音包括積極設法改善境況：向你的老闆表達你充實工作的想 法，鼓勵你的配偶尋求心理諮詢，或是成為一個政治活動家以選出一 個比較清廉的政府。忠誠是指咬緊牙關去忍受：即便工作令人窒息仍 繼續努力工作，強忍著和配偶在一起，或者即便反對政府的做法還是 支持政府。忽視包括停留在當前境況，但不那麼努力：工作做得馬馬 虎虎不被解僱就行，選擇新的愛好使你遠離你的配偶，或者拒絕投 票。 從根本上說，這些選擇都是基於控制感和獻身精神。你相信你能 實現變革嗎？你在乎不斷嘗試嗎？如果你認為你被困在當前的處境 中，如果你不願意獻身，你會選擇忽視。如果你有獻身精神，你會選"
    },
    {
      "title": "發聲+女性身份，雙重少數身份帶來雙重風險",
      "page": 86,
      "excerpt": "想法更有效，並減少向中層管理人員提出建議的時間。高層領導認為 她是不可多得的人才，能夠發現機構的問題，並且相信可以帶來改 變；並且由於單位的下級同事的青睞，她的威信進一步加強。當她同 中情局的新星分享她的看法，他們感到非常興奮，並將她提拔到更高 的位置。“年輕的員工非常欣賞她新穎的想法，並把她作為真正的榜 樣，這就使得別人更加難以反對，”梅迪納的同事蘇珊·本傑明（Susan Benjamin）說，“這鞏固了她的聲譽，並且使越來越多的人瞭解到她 的想法。” 發聲+女性身份，雙重少數身份帶來雙重風險 對於任何人來說，將傾向於規避風險的中層管理人員當作聽眾去 發表自己的意見是一種挑戰，對於卡門·梅迪納來說尤其如此——她在 一個以男性為主導的組織工作。當我第一次聽到她的故事，我天真地 認為“男人來自火星，女人來自金星”這樣的想法已經是很久遠的事 了，最終我們會依照想法的質量來進行評估，而不是依照陳述想法的 人的性別。但當我看到證據，我沮喪地發現，即使在今天，女性發表 意見仍然是非常困難的。在不同文化中，有相當多的證據顯示人們仍 舊持有強烈的性別角色的刻板印象——認為男人是有決斷力的，女人 是熱心於公共事業的。當女性發表意見，她們會冒違背性別刻板印象 的風險，導致聽眾認為她們太好強。發表意見是領導力的表現，正如 臉書首席運營官謝麗爾·桑德伯格在《向前一步》中寫道：“當一個女 孩嘗試領導者角色時，她常被貼上‘愛使喚人’ ［43］ 的標籤。” 當我分析自己收集的數據，結果令人深感不安。在一家國際銀行 和醫療保健公司，我發現，提出新的創新想法會讓男性的業績評估分 數更高，而女性則不然。其他研究顯示，發表意見次數多的男性主管 會獲得獎勵，但如果是女性主管發表意見，則會同時受到來自男性和 女性的貶低。同樣，當女性提出改進建議，管理者會認為她們的忠誠 度比男性低，而且不太可能將她們的建議付諸實施。尤其是在以男性 為主導的組織中，女性會因發表意見而付出代價。 17 ［44］ 在卡門·梅迪納第一次嘗試發表意見時，她為此付出了代價。她 說：“女性可接受的行為範圍比男性的要窄。”在她第二次復出期間， 她有了不同的體驗。由於她工作的一部分職責是將信息放到網上，因 此她在發表提高透明度的意見時不再需要擔心顯得過於激進。“20世 紀90年代初，當我把一切弄砸時，我把對實現變革的投入與職業生涯 沒有進步而感到的沮喪相混淆了。所以我總是以‘我’為中心，”梅迪納 告訴我，“而第二次則與第一次有很大的不同。我以任務為核心。”大 量研究表明，女性代表別人發表意見時，她們不再遭到強烈的反抗， 因為別人覺得她們是“熱心於公共事業”的。 毫無疑問，梅迪納面臨的道路更加崎嶇，因為她身處一個以男性 為主導的中央情報局中，而她又是波多黎各人，這使她不僅僅屬於一 個，而是兩個少數群體。新的研究表明，她的雙重少數群體的身份可 能會使她發表意見時付出的成本和得到的回報倍增。管理研究員阿什 利·羅塞蒂（Ashleigh Rosette）——一位非裔美國人，發現如果她比 白人女性和黑人男性在領導中更果斷，她所受到的對待會不同。她與 同事合作研究發現，雙重少數族群身份的成員面臨雙重危險。 ［45］ 當黑人女性失敗後，人們對她的評價比對黑人男性和白人男性或女性 領導者的更嚴厲。她們作為女性和少數族群，不符合人們的刻板印象 ——即領導者應該是白人和男性，並且一旦她們犯了錯誤，她們會遭 到更多責備。羅塞蒂的研究小組指出，對於雙重少數群體的人，失敗 是註定的。 不過有趣的是，羅塞蒂和她的同事發現，當黑人女性在行動中採 取強"
    }
  ],
  "has_toc": true,
  "extracted_at": "2026-04-25"
}