{
  "id": "local_38f000720845",
  "title": "上升星座",
  "category": "塔羅/靈性",
  "total_pages": 286,
  "toc": [
    {
      "level": 1,
      "title": "上升星座000.jpg",
      "page": 1
    },
    {
      "level": 1,
      "title": "上升星座001.tif",
      "page": 4
    },
    {
      "level": 1,
      "title": "上升星座002.tif",
      "page": 5
    },
    {
      "level": 1,
      "title": "上升星座003.tif",
      "page": 6
    },
    {
      "level": 1,
      "title": "上升星座004.tif",
      "page": 7
    },
    {
      "level": 1,
      "title": "上升星座005.tif",
      "page": 8
    },
    {
      "level": 1,
      "title": "上升星座006.tif",
      "page": 9
    },
    {
      "level": 1,
      "title": "上升星座007.tif",
      "page": 10
    },
    {
      "level": 1,
      "title": "上升星座008.tif",
      "page": 11
    },
    {
      "level": 1,
      "title": "上升星座009.tif",
      "page": 12
    },
    {
      "level": 1,
      "title": "上升星座010.tif",
      "page": 13
    },
    {
      "level": 1,
      "title": "上升星座011.tif",
      "page": 14
    },
    {
      "level": 1,
      "title": "上升星座012.tif",
      "page": 15
    },
    {
      "level": 1,
      "title": "上升星座013.tif",
      "page": 16
    },
    {
      "level": 1,
      "title": "上升星座014.tif",
      "page": 17
    },
    {
      "level": 1,
      "title": "上升星座015.tif",
      "page": 18
    },
    {
      "level": 1,
      "title": "上升星座016.tif",
      "page": 19
    },
    {
      "level": 1,
      "title": "上升星座017.tif",
      "page": 20
    },
    {
      "level": 1,
      "title": "上升星座018.tif",
      "page": 21
    },
    {
      "level": 1,
      "title": "上升星座019.tif",
      "page": 22
    },
    {
      "level": 1,
      "title": "上升星座020.tif",
      "page": 23
    },
    {
      "level": 1,
      "title": "上升星座021.tif",
      "page": 24
    },
    {
      "level": 1,
      "title": "上升星座022.tif",
      "page": 25
    },
    {
      "level": 1,
      "title": "上升星座023.tif",
      "page": 26
    },
    {
      "level": 1,
      "title": "上升星座024.tif",
      "page": 27
    },
    {
      "level": 1,
      "title": "上升星座025.tif",
      "page": 28
    },
    {
      "level": 1,
      "title": "上升星座026.tif",
      "page": 29
    },
    {
      "level": 1,
      "title": "上升星座027.tif",
      "page": 30
    },
    {
      "level": 1,
      "title": "上升星座028.tif",
      "page": 31
    },
    {
      "level": 1,
      "title": "上升星座029.tif",
      "page": 32
    },
    {
      "level": 1,
      "title": "上升星座030.tif",
      "page": 33
    },
    {
      "level": 1,
      "title": "上升星座031.tif",
      "page": 34
    },
    {
      "level": 1,
      "title": "上升星座032.tif",
      "page": 35
    },
    {
      "level": 1,
      "title": "上升星座033.tif",
      "page": 36
    },
    {
      "level": 1,
      "title": "上升星座034.tif",
      "page": 37
    },
    {
      "level": 1,
      "title": "上升星座035.tif",
      "page": 38
    },
    {
      "level": 1,
      "title": "上升星座036.tif",
      "page": 39
    },
    {
      "level": 1,
      "title": "上升星座037.tif",
      "page": 40
    },
    {
      "level": 1,
      "title": "上升星座038.tif",
      "page": 41
    },
    {
      "level": 1,
      "title": "上升星座039.tif",
      "page": 42
    },
    {
      "level": 1,
      "title": "上升星座040.tif",
      "page": 43
    },
    {
      "level": 1,
      "title": "上升星座041.tif",
      "page": 44
    },
    {
      "level": 1,
      "title": "上升星座042.tif",
      "page": 45
    },
    {
      "level": 1,
      "title": "上升星座043.tif",
      "page": 46
    },
    {
      "level": 1,
      "title": "上升星座044.tif",
      "page": 47
    },
    {
      "level": 1,
      "title": "上升星座045.tif",
      "page": 48
    },
    {
      "level": 1,
      "title": "上升星座046.tif",
      "page": 49
    },
    {
      "level": 1,
      "title": "上升星座047.tif",
      "page": 50
    },
    {
      "level": 1,
      "title": "上升星座048.tif",
      "page": 51
    },
    {
      "level": 1,
      "title": "上升星座049.tif",
      "page": 52
    },
    {
      "level": 1,
      "title": "上升星座050.tif",
      "page": 53
    },
    {
      "level": 1,
      "title": "上升星座051.tif",
      "page": 54
    },
    {
      "level": 1,
      "title": "上升星座052.tif",
      "page": 55
    },
    {
      "level": 1,
      "title": "上升星座053.tif",
      "page": 56
    },
    {
      "level": 1,
      "title": "上升星座054.tif",
      "page": 57
    },
    {
      "level": 1,
      "title": "上升星座055.tif",
      "page": 58
    },
    {
      "level": 1,
      "title": "上升星座056.tif",
      "page": 59
    },
    {
      "level": 1,
      "title": "上升星座057.tif",
      "page": 60
    },
    {
      "level": 1,
      "title": "上升星座058.tif",
      "page": 61
    },
    {
      "level": 1,
      "title": "上升星座059.tif",
      "page": 62
    }
  ],
  "intro": "",
  "chapters": [],
  "has_toc": true,
  "extracted_at": "2026-04-25"
}