{
  "id": "local_cfaefb136c1e",
  "title": "再貴也能賣到缺貨的祕密",
  "category": "其他",
  "total_pages": 352,
  "toc": [
    {
      "level": 1,
      "title": "內容",
      "page": 6
    },
    {
      "level": 1,
      "title": "介绍",
      "page": 9
    },
    {
      "level": 1,
      "title": "什麼是差異化？",
      "page": 14
    },
    {
      "level": 1,
      "title": "為什麼差異化很重要？",
      "page": 20
    },
    {
      "level": 1,
      "title": "你可以以低價打造強大的品牌",
      "page": 30
    },
    {
      "level": 1,
      "title": "品質不是差異化因素",
      "page": 39
    },
    {
      "level": 1,
      "title": "服務不是差異化因素",
      "page": 46
    },
    {
      "level": 1,
      "title": "人也不是區別的因素",
      "page": 53
    },
    {
      "level": 1,
      "title": "為什麼分辨起來這麼困難？",
      "page": 58
    },
    {
      "level": 1,
      "title": "良好差異化標準",
      "page": 64
    },
    {
      "level": 1,
      "title": "策略一 - 銷售領導力",
      "page": 68
    },
    {
      "level": 1,
      "title": "策略二 - 科技領導力",
      "page": 88
    },
    {
      "level": 1,
      "title": "策略三 - 績效領導",
      "page": 105
    },
    {
      "level": 1,
      "title": "策略四 - 下一代",
      "page": 119
    },
    {
      "level": 1,
      "title": "策略五 - 產品的製造方式",
      "page": 133
    },
    {
      "level": 1,
      "title": "策略六 - 產品製造地點",
      "page": 149
    },
    {
      "level": 1,
      "title": "策略七 - 屬性所有權",
      "page": 168
    },
    {
      "level": 1,
      "title": "策略八 – 個性",
      "page": 185
    },
    {
      "level": 1,
      "title": "策略九 - 相反立場",
      "page": 199
    },
    {
      "level": 1,
      "title": "策略第十號 – 專業化",
      "page": 216
    },
    {
      "level": 1,
      "title": "策略第十一號 – 偏好",
      "page": 254
    },
    {
      "level": 1,
      "title": "策略第十二號 – 傳承",
      "page": 282
    },
    {
      "level": 1,
      "title": "策略第十三號 – 設計",
      "page": 307
    },
    {
      "level": 1,
      "title": "你要怎麼運用這個差異化的想法？",
      "page": 326
    },
    {
      "level": 1,
      "title": "保護你的差異化理念",
      "page": 340
    },
    {
      "level": 1,
      "title": "最後的話",
      "page": 351
    }
  ],
  "intro": "殺手 差異化因素 Differentiate 19 2 月 19 日 08.indd 1 Differentiate 19 2 月 19 日 08.indd /20 下午5：32：/20 下午5：32：44 Differentiate 2 08.indd 2 2 Differentiate 2 08.indd /20 下午5：32：/20 下午5：32：45 殺手 差異化因素 13 策略 成長你的品牌 太成 威爾森·丘 Differentiate 19 2 月 19 日 08.indd 3 Differentiate 19 2 月 19 日 08.indd /20 下午5：32：/20 下午5：32：45 © 2008年馬歇爾·卡文迪許國際（亞洲）私人有限公司，由馬歇爾·卡文 迪許商業出版 新加坡 Marshall Cavendish International 1 New Industrial Road 的品牌 版權所有 未經版權人事先許可，不得以任何形式或方式（電子、機械、影印、錄 音或其他方式）複製、儲存或傳輸本出版物的任何部分。申請許可請寄 至出版商 Marshall Cavendish International （Asia） Private Limited， 新加坡 新工業路 1 號。電話：（65） ，傳真： （65） 。電子郵件：genref@sg.marshallcavendish.com。 網站：www.marshallcavendish.com/genref 出版商對本書內容不作任何陳述或保證，並明確否認任何默示保證、可 銷性或因特定目的而產生的信件，且在任何情況下均不對任何產品損失 或其他商業損害負責，包括但不限於特殊、附帶、結果性或其他損害。 其他馬歇爾·卡文迪許官邸 Marshall Cavendish Ltd. 倫敦藏紅花山 32–38 號 5 樓，EC1N 8FH • Marshall Cavendish 公司。美國紐約州塔里鎮白原路 99 號，郵編 -9001 • Marshall Cavendish International （Thailand） Co Ltd.，曼谷 Klongtoey Nua，素坤逸 21 路，Asoke 街 12 樓 253 號，郵 遞區號 • Marshall Cavendish（馬來西亞）有限公司，Times Subang，46 號地段，Subang 高科技工業園區，馬來西亞雪蘭莪州達魯 艾山 Shah Alam 號。Marshall Cavendish 是新加坡國家圖書館 委員會時代出版有限公司的商標，目錄資料 Tai， Jacky， 1970-Killer Differentis： 13 策略以擴展你的品牌 / Jacky Tai 與 Wilson Chew。 – 新加坡：Marshall Cavendish Business，約 2008 年。 P.CM。 ISBN-13：978-981-261-570-1 ISBN-10 ： 981-261-570-9 1. 品牌產品。2. 品牌（行銷）I. Chew， Wilson，1970-II.標題。 HD69。B7 658.827 — dc22 OCN由新加坡工藝印刷國際有限公司印刷。 Differentiate 2 月 19 日 08.indd 4 Differentiate 2 月 19 日 08.indd /20 下午5：32：/20 下午5：32：45 這本書獻給我的父母， 太金儀和李才來，感謝 他們所承受的所有艱 辛、所有犧牲，以及他們在養育我過程中 忍受的種種荒謬 。非常感謝 你們，爸爸和媽媽。 ~ 傑基 ~ 我很自豪能將這本書獻給 StrategiCom 所有博學的同事們。這本書每天 都因為你們每一位而變得更好 。 ~ Wilson ~ Differentiate 2 月 19 日 08.indd 5 Differentiate 2 月 19 日 08.indd /20 下午5：32：/20 下午5：32：45 內容 介绍 8 第一章 什麼是差異化？ 14 第二章：為什麼差異化很重要？ 22 第三章 你可以建立強大的品牌 基於低價 34",
  "chapters": [
    {
      "title": "內容",
      "page": 6,
      "excerpt": "Differentiate 2 月 19 日 08.indd /20 下午5：32：/20 下午5：32：45 這本書獻給我的父母， 太金儀和李才來，感謝 他們所承受的所有艱 辛、所有犧牲，以及他們在養育我過程中 忍受的種種荒謬 。非常感謝 你們，爸爸和媽媽。 ~ 傑基 ~ 我很自豪能將這本書獻給 StrategiCom 所有博學的同事們。這本書每天 都因為你們每一位而變得更好 。 ~ Wilson ~ Differentiate 2 月 19 日 08.indd 5 Differentiate 2 月 19 日 08.indd /20 下午5：32：/20 下午5：32：45 內容 介绍 8 第一章 什麼是差異化？ 14 第二章：為什麼差異化很重要？ 22 第三章 你可以建立強大的品牌 基於低價 34 第四章 品質不是區別因素 46 第五章 服務不是差異化因素 56 第六章 人也不是區別因素 66 第七章 為什麼這麼難分辨？ 72 第八章 良好差異化標準 80 第九章 策略第一 – 銷售領導力 86 第十章 策略第二號 – 科技領導力 106 第十一章 策略第三號 – 績效領導 122 Differentiate 2 月 19 日 08.indd 6 Differentiate 2 月 19 日 08.indd /20 下午5：32：/20 下午5：32：45 第十二章 策略第四號 – 下一代 138"
    },
    {
      "title": "介绍",
      "page": 9,
      "excerpt": "Differentiate 19 2 月 19 日 08.indd /20 下午5：32：/20 下午5：32：45 介绍 過去三年來，我們曾在許多品牌研討會、會議和論壇上演講。我們也為 新加坡公司舉辦過許多品牌工作坊。我們經常討論的一件事是所有強大 品牌都建立在的十條品牌法則，無論是本地、區域還是全球品牌。我們 經常被問及是否有針對小型企業的特殊規定，因為我們接觸的許多公司 都是來自新加坡的中小企業。我們經常被問到這個問題，因為當小企業 主看到我們用來示範品牌原則的大品牌時，他們的眼神會變得呆滯，嘴 巴微張，心裡會想： 「啊！但這些規定只適用於大品牌。我是小企業。這些規則不適用於 我。」 好消息和壞消息是。壞消息是，小型企業沒有特別的品牌規則。你小不 代表你會得到特殊待遇。但好消息是，品牌規則就像數學：一加一等於 二。它們是普遍適用的，無論你是大還是小;西方還是亞洲;B2B 或是 B2C。而那些讓大品牌成為今日樣貌的規則，也能幫助你的企業成 長。 是時候醒來，為你的品牌做些什麼了 如果你仍然認為品牌規則不適用於你這個小企業，我們建議你徹底改變 觀點，因為這對你的品牌幫助不大。這些規則確實適用於你，而你的企 業能否存活，很可能取決於你理解並落實這些規則 差異化 208.indd 8 Differentiate 2 月 19 日 08.indd /20 下午5：32：/20 下午5：32：45 規則。所以，是時候超越那些大品牌的現狀了。深入探究他們的過去， 了解它們謙卑的起點，我們可以保證你會發現一個簡單的真相：每個大 型成功品牌，都是從一個小而掙扎的新創公司起步。和你的公司沒什麼 兩樣，而且在很多情況下，他們的狀況可能比你現在還糟。 根據 《商業週刊 》年度「百大品牌」排名，可口可樂、Microsoft、 IBM、通用電氣、諾基亞、豐田、英特爾、麥當勞、迪士尼和賓士是全 球十大最具價值品牌之一（ 商業週刊 ，年8月）。這些公司曾經也很小。他們也曾經掙扎過。他們不會到 處問品牌專家，像他們這樣的小企業是否有品牌規則可以遵循。他們尋 找——並找到——策略，幫助他們轉型成為強大且強大的全球品牌，並 持續執行這些策略。這就是他們成功的原因。 如果他們遵循一些為小型企業設計的品牌規則，我們相信他們會繼續保 持小型企業的身份。想想看。如果有針對小型企業的品牌規則，那它們 就是為小型企業設計的，並且是在假設小型企業會使用這些規則的前提 下制定的。那是什麼意思？意思是，如果你想遵守這些規則，你就想保 持小企業的身份。你不希望那樣。你想要的是設計來將你的小企業轉變 為大型品牌的規則。 並非所有人都能成為全球品牌。事實是，大多數人仍會保持相對小規模; 許多人甚至會失敗。但如果你了解品牌規則並善用它們，你就能給你的 企業一個在時間考驗和激烈競爭中存活的一線希望。有希望你的小企業 明天能成為中型企業。一旦成為中型企業，誰知道隔天會發生什麼？一 步一步來。做正確的事，用正確的方式做事。 誰想成為百萬富翁？ 如果你想成為百萬富翁，你應該效法百萬富翁。但你應該試著做他們成 功前所做的事。如果你只是簡單地模仿他們現在成功後所做的事——例 如住在昂貴的房子裡、開著破舊的車、在高級餐廳用餐、穿上高級時尚 品牌等等 ——你很快就會破產。這是常識！你不需要是金融高手也能理解這點。 Differentiate .indd 9 Differentiate .indd /20 下午5：32：/20 下午5：32：45 同樣的道理也適用於你的事業。如果你想成為一個成功的品牌，你要看 看成功品牌"
    },
    {
      "title": "什麼是差異化？",
      "page": 14,
      "excerpt": "2008/20 下午5：32：/20 下午5：32：46 第一章 Differentiate .indd 14 Differentiate .indd /20 下午5：32：/20 下午5：32：46 什麼是差異化？ Differentiate .indd 15 Differentiate .indd /20 下午5：32：/20 下午5：32：46 它說過「需求是發明之母」。而需求無疑是四千年前品牌標誌發明的原 因。當時的牛主迫切需要找到辨別彼此牛隻的方法，並想出一個簡單卻 巧妙的解決方案。他們製作了烙鐵，一端刻有主人的標誌或標誌。烙鐵 被燒到紅熱，然後在牛的臀部烙下一個獨特的標記。 完成這些後，牛主們就能輕易分辨牛隻。這很簡單，但確實有效。 品牌塑造不只是關於標誌設計，雖然仍有太多人抱有這種誤解。是的， 它確實是從一個標誌開始的 4,000 但那個標誌是用來區分牛的。 品牌塑造不只是關於標誌。品牌塑造是關於你如何使用那個標誌。 而差異化的需求，依然是品牌至今仍然存在的原因。它的形式可能改變 了，但它的功能依然存在，那就是讓你的牛從競爭對手中脫穎而出—— 只是現在的「牛」變成了公司、產品和服務。其中一些「牛」也以人的 形式出現——是的，現在連人都需要品牌塑造。 從這個角度看，差異化可以說是將本質上是商品的東西轉變成品牌的過 程。牛就是牛。讓我們的牛與你的牛不同之處，就是牠們臀部上的標誌 及其代表的意義。 依雲銷售水，而水是豐富的資源——畢竟全球80%的土地都被水覆蓋 ——但讓依雲成為如此強大的品牌，是其水經過阿爾卑斯山自然過濾過 程，並富含必需礦物質。水就是水，除非水有差異化，而依雲的水之所 以有差異化，是因為它來自阿爾卑斯山。 Differentiate 19 2 月 19 日 08.indd 16 Differentiate 19 2 月 19 日 08.indd /20 下午5：32：/20 下午5：32：46 什麼是差異化？ 17 獨特的賣點 差異化是為你的品牌創造獨特的銷售主張。 獨特銷售主張（Unique Selling Proposition，簡稱 USP）是廣告傳奇人 物羅瑟·里夫斯（Rosser Reeves）所創造的術語。在他 1961 年的著作《 廣告中的現實》（Reality In Advertising）中，他將此定義為競爭對手要 麼不提供，要麼無法提供的一個提案。 許多人認為獨特銷售主張作為行銷概念已過時且不相關。在我們看來， 獨特賣點（USP）或許是個老概念，但這並不讓它在今天比 1961 年時 更具說服力。差異化是讓品牌從眾多相似競爭者中脫穎而出的關鍵。沒 有差異化，就無法建立強大的品牌。要與眾不同，你必須獨一無二。這 使得獨特賣點（USP）成為一個非常重要的概念，因為擁有獨特賣點代 表你是獨一無二的。擁有獨特賣點意味著你以與顧客相關的方式被區隔 化。然而，仍有許多原因讓許多人忽視它。 第一，人們往往隨著時間忘記什麼有效、什麼無效。在他的著作 《Trout On Strategy》中，1969 年發明定位概念的傑克·特勞特寫道，這 是許多企業一旦成功後會受到影響的現象。他稱之為 FWMTF（忘記了 什麼讓他們成名）症候群。 我們同意。看看你身邊的公司，通常可以追溯到他們最初的獨特賣點。"
    },
    {
      "title": "為什麼差異化很重要？",
      "page": 20,
      "excerpt": "Differentiate 19 2 月 08.indd 21 Differentiate 19 2 月 08.indd /20 下午5：32：/20 下午5：32：46 22 個致命差異化 第二章 Differentiate .indd 22 Differentiate .indd /20 下午5：32：/20 下午5：32：46 為什麼差異化很重要？ Differentiate .indd 23 Differentiate .indd /20 下午5：32：/20 下午5：32：47 請看看下面這兩個燈泡。它們都是全新的、100 瓦的燈泡。如果你必須 為辦公室購買燈泡，你會選哪個品牌——Blue Sparks 還是 White Heat？嗯，你其實很難分辨兩者的差異，對吧？ 那你怎麼知道該買哪一款？當然是《白熱》！因為它是50 比另一個品牌便宜幾分錢，這就是原因！ 藍色火花 白熱戰 $3 $2.50 然而，Blue Sparks 價格較高其實有個很好的原因：它更耐用。Blue Sparks 的燈泡壽命是 100 小時，而 White Heat 則是 60 小時。所以， Blue Sparks 的可用壽命是每小時 3 美分，而 White Heat 則是 4.2 美 分。從長遠來看，Blue Sparks 比較便宜，但買家一眼看不出來，這也 是它的問題所在。 當你的潛在顧客無法或無法察覺差異時，他們會選擇較便宜的替代方 案。這就是為什麼差異化如此重要，尤其是在當今競爭激烈的市場中， 顧客選擇眾多。如果你沒有差異，或你的差異不容易被察覺，那你最好 選擇非常低的價格。 然而，價格競爭是個危險的舉動，因為一旦你失去價格優勢給低成本國 家的競爭者，差異化 2008年2月19日。 Differentiate 2008 年 2 月 19 日.indd /20 下午5：32：/20 下午5：32：47 為什麼差異化很重要？ 25 你將失去顧客購買的理由。這就是為什麼我們總是警告那些在價格上競 爭的公司，務必確保他們能長期維持低價，因為很多時候，除了這些公 司吸引人的價格外，沒有其他理由購買。 如果你覺得現在市場很艱難，我們有驚人的消息告訴你：這才剛開始。 競爭者就像飛蛾撲鼻——他們被金融吸引。如果你的市場或類別火熱， 自然會吸引一群競爭者爭奪競爭。他們的想法是：為什麼要讓你獨佔市 場？如果情況反過來，你大概也會這麼想。事實上，你可能已經開始這 麼想了—— 將您的公司推向您認為熱門或快速成長的新市場或類別。 競爭不僅會變得更激烈，競爭者數量也會增加。如果你是像 Blue Sparks 這樣有創新產品或服務的公司，務必清楚界定並妥善傳達你的差 異。否則，另一種選擇就是以價格競爭。總會有競爭者後期加入，試圖 透過滲透式定價策略搶走你的市場份額。有些公司之所以成功，是因為 他們的商業模式完全設計得很低成本。如果你無法在價格上匹敵他們， 那你最好確保自己有差異化。"
    },
    {
      "title": "你可以以低價打造強大的品牌",
      "page": 30,
      "excerpt": "你可以打造強大的力量 品牌基於低價 Differentiate 2008 年 2 月 19 日.indd 35 Differentiate 2008 年 2 月 19 日.indd /20 下午5：32：/20 下午5：32：48 許多品牌專家會告訴你，你需要建立一個強大的品牌，這樣就不必在價 格上競爭。我們的看法也差不多。然而，我們不會告訴你，如果你只在 價格上競爭，就無法建立強大的品牌，因為那根本不是真的。 即使你的策略是以價格競爭，也能建立強大的品牌。 成為市場上最便宜的品牌並沒有什麼不對。不知為何，人們往往認為能 收取溢價的品牌是那些真正打造它的品牌。但我們的想法不同。對我們 來說，一個成功的品牌是能夠主導其品類，並在過程中獲得不錯的銷售 額，不論是高級品牌還是平價品牌。當然，能夠賣出更高的價格固然不 錯，但那些賣得便宜的品牌也能成為強勢品牌。 當我們見到 eSys Technologies 董事長 Vikas Goel 時，他告訴我們，基 本上任何商人都能經營兩種類型的公司 ——一個專注於創新，另一個專注於效率。 Vikas 非常清楚 eSys 是什麼樣的企業動物：它專注於從每一個流程中榨 取最後一絲效率。這就是為什麼 eSys 能以 399 新幣出售其在新加坡樟 宜北工廠製造的電腦，仍能取得專業成績。我們認為 eSys 有潛力成為 一個建立在低價公式上——或以 Vikas 的 說真的，效率科學平台——如果它願意的話。令人難以置信的不是 eSys 電腦便宜，而是它們即使建在像新加坡這樣高成本地區，卻依然如此便 宜。 許多品牌都是建立在低價公式之上。關鍵在於，你必須能夠在來自巴 西、俄羅斯、中國和印度等多個低成本國家的激烈價格競爭面前保持穩 定。要成為強大的低價品牌，你需要擁有結構性的成本優勢 ，這意味著 你的成本效益必須內建於你的商業模式，並成為你基礎設施不可或缺的 一部分。 Differentiate 2 月 19 日 08.indd 36 Differentiate 2 月 19 日 08.indd /20 下午5：32：/20 下午5：32：48 你可以基於低價建立強大的品牌 37 將營運遷至低成本國家、壓縮供應商及壓低員工薪資，並不代表結構性 的成本優勢，因為事實並非如此，且這些措施很容易被競爭對手模仿。 我們將與您分享一些基於低價公式建立的強大全球品牌及其獨特的結構 性成本優勢，幫助您判斷這種低價打造強大品牌的途徑是否適合您的公 司。 戴爾 1984年，戴爾成為第一家直接向終端用戶銷售電腦的公司。當時，許多 人認為戴爾無法成功，因為電腦並非傳統上以這種方式銷售。麥可·戴爾 顯然是個不讓傳統阻礙的人。他是一位持不同思維的遠見者。然而，讓 系統運作並不容易。成本上的優勢非常巨大。透過消除中間商，戴爾享 有比傳統競爭對手更低的營運成本，節省的費用也轉嫁給客戶，且不影 響其利潤率。 直銷通路為戴爾帶來了競爭對手無法——也至今無法——匹敵的結構性 成本優勢。它將戴爾從車庫轉型為領導者。戴爾多年來一直是銷量第一 的電腦。最近它把第一名的位置讓給了惠普（HP），但這並不代表其商 業模式會被動搖。它依然非常有競爭力，結構性的成本優勢也非常巨 大。 我們認為惠普超越戴爾的原因之一是筆記型電腦的爆炸性成長。戴爾在 桌上型電腦領域闖出了名號，但如今，筆記型電腦已在銷售量上超越桌 上型電腦，隨著企業世界逐漸非有線化、辦公室電腦轉向行動，筆電將 持續超越桌機。例如，這本書大部分內容是在咖啡館用 IBM ThinkPad T60 筆電寫成的，而非在辦公室"
    },
    {
      "title": "品質不是差異化因素",
      "page": 39,
      "excerpt": "Differentiate 2 月 19 日 08.indd /20 下午5：32：/20 下午5：32：49 Differentiate 2 月 19 日 08.indd 45 Differentiate 2 月 19 日 08.indd /20 下午5：32：/20 下午5：32：49 第四章 Differentiate 2 月 19 日 08.indd 46 Differentiate 2 月 19 日 08.indd /20 下午5：32：/20 下午5：32：49 品質不是差異化因素 Differentiate 2 月 19 日 08.indd 47 Differentiate 2 月 19 日 08.indd /20 下午5：32：/20 下午5：32：49 在你把這本書丟進垃圾桶並公開之前，讓我們先聲明，品質在打造品牌 中非常重要。你無法靠煙霧彈和幻象來打造強大的品牌。 如果你的產品或服務品質無法與競爭對手匹敵，也無法建立強大的品 牌。然而，這並不代表擁有更高品質的產品或服務就能讓你的品牌脫穎 而出。這不是很奇怪的矛盾嗎？如果沒有品質，你就無法建立強大的品 牌。 右。 但有品質並不能幫助你區隔品牌？又說對了。 品質是必備條件，但如今，品質不過是進入這個叫做市場的入場券。也 就是說，為了讓你的品牌有機會被顧客考慮，它必須具備品質。沒有品 質，你甚至無法被邀請參與遊戲。這就是你品牌必須生活的高度競爭現 實。 品質依然重要，但不幸的是，品質已成為一種商品，正如我們先前所 說，商品之間幾乎無法區分。因此，品質已不再是差異化的因素。 這似乎不太公平，因為你們許多人花了大量時間和心力確保品質達到頂 尖，然而我們兩個卻告訴你們，光有品質已經不夠了。但事情就是這 樣。本章我們想系統性地探討原因。 大家都代表品質 我們在定期舉辦的品牌研討會和工作坊中，經常遇到許多公司。當我們 問這些公司有什麼獨特或特別之處時，大多數人會很快回答：「我們代 表品質。」這其實很棒！如果每家公司都相信品質並付諸實踐，世界會 變得更美好。 Differentiate .indd 48 Differentiate .indd /20 下午5：32：/20 下午5：32：49 品質不是差異化因素 49 然而，從品牌的角度來看，當每個人都代表品質時，實際上沒有人真正 代表品質。這聽起來可能矛盾，但想想看：品牌塑造就是關於差異化。 如果每家公司都只代表品質，就沒有差異化。那又怎樣？人們會買價格 較低的品牌。 品質只有在有足夠多公司勇敢（或愚蠢）站出來大聲宣稱「我們不是品 質公司」時，才能成為差異化的因素。只有那時，才會出現兩個對立陣 營——一個堅持品質，另一個不代表。這種情況發生的機率有多大？我 們認為教黑猩猩駕駛波音747，比教那些不自稱品質的公司要容易得 多。 如果我們把你的願景聲明和競爭對手的並列，扣除公司名稱和標誌，你 的員工（甚至高層管理）能分辨出哪個屬於你的公司，機率有多大？沒 錯。 每個人都代表品質。你們努力透過推行像是全面品質管理、六標準差、 零缺陷等計畫來提升品質水準。你們兌現了這個品質承諾。我們相信你"
    },
    {
      "title": "服務不是差異化因素",
      "page": 46,
      "excerpt": "Differentiate 2008 年 2 月 19 日.indd /20 下午5：32：/20 下午5：32：49 Differentiate 2 月 19 日 08.indd 55 Differentiate 2 月 19 日 08.indd 年2月20日 下午5：32：年2月20日 下午5：32：50 第五章 Differentiate 19 2 月 19 日 08.indd 56 Differentiate 19 2 月 19 日 08.indd 年2月20日 下午5：32：年2月20日 下午5：32：50 服務不是差異化因素 Differentiate 2 月 19 日 08.indd 57 Differentiate 2 月 19 日 08.indd 年2月20日 下午5：32：年2月20日 下午5：32：50 同樣品質，服務也成為某種商品。 人們期望優質服務是交易的一部分。如果你無法提供，你也無法在市場 上競爭。因此，服務不再是差異化的因素。 然而，產品品質和服務品質之間有很大的差別。服務品質對競爭對手來 說極難複製，因為它不是無生命的物件。他們不能簡單購買能複製你服 務品質的技術或機器，因為服務通常是由人類提供，幾乎無法標準化。 他們有自己的主見，並不總是照指示做。 事實上，他們不僅不總是做應該做的事，還經常做不該做的事。他們不 該抽菸，因為吸菸有害，但很多人還是會抽菸。他們不該亂丟垃圾，因 為亂丟垃圾會破壞環境，但每個城市仍有不悔改的亂丟垃圾者困擾著。 你訓練員工持續提供高品質，這也讓競爭對手模仿你的服務品質是不公 平的。 下次你走進咖啡館買咖啡時，看看咖啡師在工作。 即使每次都是同一個人做咖啡，他或她也不一定每次都完全一樣。而且 每個咖啡師都會用他們獨特的風格來做。很有趣，不是嗎？ 服務品質不僅競爭對手難以複製，甚至在你自己公司內也極難複製。最 難做到的就是一致性。產品可以在外觀、手感、功能、效能及其他重要 參數上保持一致，但服務品質就很難做到。即使是同一個人交付，品質 也會時不時變化。這歸因於人性。 有些專家試圖利用六標準差的服務品質實踐來消除差異。我們只能說： 「祝你好運。」Jacky 參與了 Differentiate 2008 年 2 月 19 日。indd 58 Differentiate 19 2 月 19 日 08.indd 年2月20日 下午5：32：年2月20日 下午5：32：50 服務不是差異化因素 59 過去有六標準差計畫，試圖在服務提供上保持一致，他注意到結果並不 令人鼓舞。但仍有希望。 因為服務品質很難做到完美，它能成為你公司強大的差異化因素。但前 提是你必須做到最好。如果你將服務品質放在一個獨立的行列，並確保 它持續以高標準交付，無論客戶是誰、在哪個國家，你將擁有難以置信 的競爭優勢。 但如果服務可以作為差異化指標，為什麼我們不把它納入13條差異化規 則？有三個原因。 第一，這極難達成，失敗的機率與成功一樣高。毫無疑問，回報豐厚， 但有太多無法控制的變數。因此，只有當你能達到比競爭對手更高的服 務品質並持續複製時，才應該使用服務作為差異化。 第二，顧客越來越被寵壞，部分原因是服務品質顧問會在每個機會上台"
    },
    {
      "title": "人也不是區別的因素",
      "page": 53,
      "excerpt": "Differentiate 2 月 19 日 08.indd 年2月20日 下午5：32：年2月20日 下午5：32：50 第六章 Differentiate .indd 66 Differentiate .indd 年2月20日 下午5：32：年2月20日 下午5：32：50 人們也同樣如此 這不是差異化因素 Differentiate 2 月 19 日 08.indd 67"
    },
    {
      "title": "為什麼分辨起來這麼困難？",
      "page": 58,
      "excerpt": "他們幫助支持差異化的理念。他們幫助讓它活起來。他們幫助投射並傳 達這個理念。但如果沒有那個定義品牌本質的理念，即使是最優秀的人 也無法幫助你成長。 簡而言之 你的員工就像陽光。你的顧客就像一張紙，陽光必須燒穿它。（畢竟， 如果你的員工無法打動顧客，生意就無法進行。）陽光本身無法燒穿一 張紙。太陽釋放數百萬千瓦的能量，但儘管如此，陽光對長期曝露的紙 張所能做的最好效果，或許也只是讓它變黃。 陽光要在紙上燒出洞，必須用放大鏡之類的東西聚焦。 那支放大鏡就是你的差異化點子。有了差異化點子，你的員工才能專 注，只有當他們都專注（大家唱同一首歌、跳同一支舞）時，才能帶來 改變並取得突破。我們認為這是一個恰當的比喻，別忘了你的放大鏡。 Differentiate 2008 年 2 月 19 日.indd 71 Differentiate 2008 年 2 月 19 日.indd /20 下午5：32：/20 下午5：32：52 第七章 Differentiate .indd 72 Differentiate .indd /20 下午5：32：/20 下午5：32：52 為什麼會這樣 差異化邪教？ Differentiate .indd 73 Differentiate .indd /20 下午5：32：/20 下午5：32：52 甚至 那些真心相信差異化是建立強大品牌唯一方法的公司，可能會最終 擁有完全沒有差異化的品牌——這並非因為他們缺乏努力。創造有意義 的差異化已成為極為困難的教派。這就是為什麼當你環顧四周，看到成 千上萬的品牌試圖吸引你的注意、贏得你的錢包時，你會看到許多傑出 的。並不是說它們不好;只是它們看起來都差不多而已。在當今的市場 中，同質性不是資產。它等同於死亡之吻。那麼，為什麼公司要區隔化 卻如此困難呢？ 超級競爭 企業對成長有著無法滿足的渴望。每個人都認為這是件好事，但公司成 長的幅度有限。一旦公司在某個市場達到天花板，就有兩個選擇。一是 地理擴張：將現有資產銷售給其他市場的客戶。第二種是延伸產品線， 意即公司進入其他類別以提升銷售。 無論公司選擇以何種方式擴張，都會助長過度競爭。以前面的藍火花和 白熱燈泡為例。現在，假設藍火花的原始市場是新加坡，而白熱的市場 是中國。 在 Blue Sparks 耗盡新加坡的成長機會後，可能會擴展到像中國這樣的 新市場。突然間，White Heat 在中國發現自己有個新競爭對手就在自己 後院。而 Blue Sparks 並非孤軍奮戰。 其他國家的燈泡品牌，也可能會進入中國市場以求成長。因此，中國的 燈泡市場變得擁擠且競爭激烈。 Differentiate 2008 年 2 月 19 日.indd 74 Differentiate 2008 年 2 月 19 日.indd /20 下午5：32：/20 下午5：32：52 為什麼區分起來這麼困難？ 75 但《White Heat》面臨的問題才剛剛開始。不僅要抵禦外來入侵者，還"
    },
    {
      "title": "良好差異化標準",
      "page": 64,
      "excerpt": "評選標準 為了一個好的差異化 Differentiate 19 2 月 19 日 08.indd 81 Differentiate 19 2 月 19 日 08.indd /20 下午5：32：/20 下午5：32：53 我們總是告訴公司與眾不同很重要，但同時也告訴他們，更重要的是要 用一個好點子與眾不同，而不是愚蠢的點子。評估差異化因素的標準是 什麼？為了簡化起見，我們使用三個衡量標準。 相關性 在第一章中，我們提到你的品牌必須以符合顧客需求的方式與眾不同。 然而，要找出現今相關的差異化因素卻非常困難。與眾不同很容易。以 符合顧客需求的差異化，大多數執行長會因此熬夜到深夜。嗯，當 Wilson 試圖為我們的財務團隊制定相關的差異化策略時，確實讓他熬夜 了許多夜晚。現在，試圖為客戶制定相關的差異化策略，讓 Wilson 和 Jacky 夜不能寐。（俗話說，這是骯髒的工作，但總得有人做。）舉例 來說明這個概念，假設我們有一家製造無線射頻識別陽離子（RFID）感 測器的公司，而這家公司能讓感測器的讀取準確率達到 99.9%。最近的 競爭對手感測器只能讀取 98.7%的準確率。第一家公司實際上擁有性能 優勢（而績效領導其實是很好的差異化因素）——這在對性能敏感的產 品或服務類別中尤其明顯，例如醫療掃描器或微晶片。 1.2%的差異對顧客有關聯嗎？很可能有，但差異很小，視顧客而定。如 果客戶是最高安全級別監獄，需要知道所有囚犯同時在哪裡，那麼1.2% 的差異可能天差地遠。如果客戶是物流公司，運送低價值物品如橡膠 鴨，那麼1.2%可能就不太相關。有些類別中，1.2%的差距是生死之 差。有些類別中，1.2%的差距是生死之差。有些類別則無關緊要。 Differentiate .indd 82 Differentiate .indd /20 下午5：32：/20 下午5：32：53 良好差異化標準 83 你需要判斷你的差異點是否與客戶相關。 這對某些人可能有意義，但對其他人則不然。既然你無法讓所有人都滿 意，我們建議你更關注對你最優秀客戶相關的內容。 可迫害性 並非所有差異化因素都同樣受歡迎。有些差異化比其他的更受歡迎。你 必須確保你的差異化是其中之一。然而，如果某一類別中所有理想的差 異化都已被採用，你會接受較不理想的嗎？是的，如果這些差異化仍足 夠好，能幫助你打造強大的品牌。 讓我們來看看一個容易理解的類別——汽車。像是聲望、性能、安全和 可靠性等屬性相當受歡迎。擁有一項理想的屬性可以成為強而有力的差 異化因素，正如我們將在第15章更詳細討論的那樣。 那麼，汽車產業中誰擁有什麼？自從賓士發明汽車以來，它有奢侈的權 利是首選，並且選擇了聲望。 它透過設計出比其他任何車型都高出一級（甚至兩級）的車輛，來承擔 這個差異化的責任。 BMW 後來才推出，但找到了另一個值得擁有的優勢—— 性能。數十年來，它的口號是「終極駕駛機器」。 最近改成「純粹駕駛快感」，這口號較弱，因為它不像原版那樣表達 「性能」。但性能是個值得追求的差異化因素。 Volvo 無法擁有這兩個極具吸引力的差異化優勢;德國人早已取得它們。 但這家瑞典汽車製造商找到了自己的優勢——安全。雖然不那麼吸引 人，但仍將 Volvo 打造為強大的品牌。 如我們先前討論過，可靠性是定義 Ned Toyota 的差異化因素，至今仍 是如此。 這四家汽車公司之所以是強勢品牌，是因為它們找到了理想的差異化優"
    },
    {
      "title": "策略一 - 銷售領導力",
      "page": 68,
      "excerpt": "第九章 Differentiate 2 月 19 日 08.indd 86 Differentiate 2 月 19 日 08.indd /20 下午5：32：/20 下午5：32：53 策略一 – 銷售領導 Differentiate .indd 87"
    },
    {
      "title": "策略二 - 科技領導力",
      "page": 88,
      "excerpt": "這是一個有根據的說法，因為要成為國際啤酒，必須在國際上銷售，而 在所有亞洲啤酒品牌中，虎啤的國際銷售額（指其國外銷售）以銷量計 是最高的。虎啤是否採用這種策略，則取決於公司自身。我們在這裡展 示的是，像虎啤這樣的品牌如何巧妙地取得銷售領導地位。 Differentiate .indd 104 Differentiate .indd /20 下午5：32：/20 下午5：32：55 Differentiate 19 Fel 08.indd 105 Differentiate 19 Fel 08.indd /20 下午5：32：/20 下午5：32：55 章節 10 Differentiate .indd 106 Differentiate .indd /20 下午5：32：/20 下午5：32：55 策略二 – 科技領導 Differentiate 19 2 月 19 日 08.indd 107 Differentiate 19 2 月 19 日 08.indd 107"
    },
    {
      "title": "策略三 - 績效領導",
      "page": 105,
      "excerpt": "2008/20 下午5：32：/20 下午5：32：57 策略三 – 績效領導 Differentiate 19 2 月 19 日 08.indd 123 Differentiate 19 2 月 19 日 08.indd /20 下午5：32：/20 下午5：32：57 你正在觀看一場比賽：「烏龜對野兔」。你知道烏龜最後會贏，因為兔 子會過度自信地小睡一會兒。這讓緩慢而穩定的烏龜得以追上並超越 他。不過，你還是會押注那隻野兔。為什麼？因為它比較快。 同樣地，在商業領域，任何高效能的產品都會脫穎而出並被記住。這就 是為什麼它是個很好的差異化因素。 就我們而言，askOxford 定義了「績效」這個詞。 com，是「 機器或產品的能力 」。 性能較佳的機器或產品，本質上會比競爭對手擁有更好的功能。如果它 設計成能非常快速地執行複雜計算（就像電腦一樣），那麼效能就會以 複雜計算的速度來決定。在豪華車中，高性能可能意味著能夠舒適且安 靜地快速行駛。效能更好的秤應該是更準確的（而不是告訴你比實際體 重輕了五公斤）。 績效衡量標準因類別而異。有些類別對績效更敏感，而在計算、醫療設 備與物流等類別中，績效領導力可以用來區隔你的品牌。 但效能和科技類似，你必須努力才能維持優勢。一旦有人在這方面擊敗 你，你就不再有分辨因素。如果你能迅速重新取得領先優勢，情況還算 不錯，但如果讓時間過太久，對品牌的後果可能非常嚴重。 在決定是否能以效能作為差異化因素之前，需要考慮幾個因素： Differentiate .indd 124 Differentiate .indd /20 下午5：32：/20 下午5：32：57 策略三 – 績效領導力 125 1. 這個類別對績效有多敏感？ 如果績效對產業來說不是關鍵，那麼為了取得績效優勢而拼命是沒有意 義的。 舉例來說，如果你是葡萄酒製造商，速度表現可能不比品質重要。畢 竟，葡萄需要時間生長，葡萄酒也必須成熟才能裝瓶。因此，一個能比 競爭對手更快生產葡萄酒的品牌，可能不會有任何優勢。在這類情況 下，表現並非關鍵。事實上， 「高性能」釀酒師——能開發出能在三個月內熟成葡萄酒而非典型18個 月的工藝——可能會被懷疑。人們可能會覺得這款酒不如新酒好，因為 喝酒者已經習慣認為舊酒比新酒更好。 像半導體這樣的類別會對效能敏感，因為半導體的性能會影響電腦的速 度 ——儘管英特爾極力讓我們相信微晶片（尤其是英特爾品牌的微晶片） 是讓電腦變得非常快速的關鍵。事實上，每個組成部分都有其角色，正 如我們將說明的。 電腦的所有部分彼此連接——大多透過銅（或其他金屬）連接器——而 這些零件間資料傳輸的速度也會影響電腦的整體速度。由於金屬連接器 傳輸資料的上限，這種速度很快可能會趨於穩定。 如果一家公司能打造出以 fi bre 光學為基礎的連接器，以光速傳輸資 料，那麼它就能利用效能作為差異化因素，因為這種效能在運算世界中 至關重要。 2. 你的客戶願意為表演付費嗎？"
    },
    {
      "title": "策略四 - 下一代",
      "page": 119,
      "excerpt": "12 Differentiate .indd 138 Differentiate .indd /20 下午5：32：/20 下午5：32：58 策略四 – 下一代 Differentiate 19 2 月 19 日 08.indd 139 Differentiate 19 2 月 19 日 08.indd /20 下午5：32：/20 下午5：32：58 我們從來沒有想過穿直排輪、戴上 Oakley 太陽眼鏡、把 iPod 綁在手臂 上，然後試著在東岸公園大道滑直排輪時看起來酷。並不是我們知道自 己笨拙，可能會花更多時間仰躺而不是站著，而是因為我們沒有小孩。 我們見過中年人為了孩子而在這些裝置上掙扎，孩子們也想這麼做。他 們只是想當個時髦的家長，跟上潮流。 大多數時候，我們從這些中年人臉上看到的—— 尤其是男性——是恐懼。不僅是害怕重摔，可能需要昂貴的髖關節置換 手術，還有害怕被認為不在狀態。 你們這些屬於這類的人（無意雙關）可以隨便爭辯，說你們溜直排輪是 因為愛孩子，想和他們一起做事（我們不懷疑這點）。但大多數人不願 承認的更深層原因是：人們害怕被視為過時。 這就是為什麼他們做了本該交給孩子的事情。也許等我們有了孩子，我 們也會這麼做，但我們很懷疑。如果你認識我們，你會發現繞著物體彎 曲光束比彎曲我們自己還容易。 害怕被貼上恐龍標籤，正是人們緊跟最新潮流、時尚、手機、汽車、管 理理論、小玩意兒、小玩意兒和炫技——基本上是所有事物的最新潮 流。沒有人想因為覺得自己會輸而被落在侏羅紀時代。你可以把這看作 人類天生渴望進步，或是可憐的人類狀況，讓他們成為老鼠競賽的奴 隸。 我們怎麼看？因為我們是品牌顧問，所以盡量不花時間去想這些事情。 我們看待事物的現狀，然後嘗試判斷客戶是否能利用這個機會建立強大 的品牌並爭取更多業務。你可以叫我們冷酷無情的傭兵，但如果你是我 們的客戶，我們相信你不會希望我們有別的選擇。（我們很感動，區分 2 月 19 日 08.indd 140 Differentiate .indd /20 下午5：32：/20 下午5：32：59 策略四 – 下一代 141 在這最後一句話後面加上笑臉，但這是一本嚴肅的商業書籍，我們的編 輯不允許我們這麼做。） 因為人就是這樣，成為下一代產品或服務，可以成為品牌區隔的強大方 式。人們總是在尋找新事物。新事物很有趣。而且很刺激。除此之外， 新事物打造了世界上許多最優秀的品牌。 成為下一代真的那麼重要嗎？ 當你的品牌定位為下一代（任何東西）時，你就會被注意到。這還不能 讓你立刻成交，但要成交，你必須先被邀請坐到談判桌前。而以下一代 為基準來區分化，可能就是你的邀請卡。 如我們所提，人們有一種幾乎病態的衝動，想要站在最前線。他們會檢 查所有新事物。當你是新手時，你會被忽視。媒體會談論你。潛在顧客 也會如此。 當然，你必須向世界傳達你是新手，或是擁有新事物。而你有兩種方式 可以做到這一點。 首先，你可以讓競爭對手看起來像是過時的殘餘。你可以把恐龍標籤掛 在上面，讓它們看起來過時。這讓顧客有理由不去購買，因為沒有人想"
    },
    {
      "title": "策略五 - 產品的製造方式",
      "page": 133,
      "excerpt": "章節 13 Differentiate 19 2 月 19 日 08.indd 154 Differentiate 19 2 月 19 日 08.indd /20 下午5：32：/20 下午5：32：59 策略五 – 產品如何製造 Differentiate .indd 155"
    },
    {
      "title": "策略六 - 產品製造地點",
      "page": 149,
      "excerpt": "14 Differentiate 2008 年 2 月 19 日.indd 170 Differentiate 2008 年 2 月 19 日.indd /20 下午5：33：/20 下午5：33：01 策略六 – 產品製造地點 Differentiate 19 2 月 19 日 08.indd 171"
    },
    {
      "title": "策略七 - 屬性所有權",
      "page": 168,
      "excerpt": "策略七 – 屬性所有權 Differentiate 19 2 月 19 日 08.indd 191"
    },
    {
      "title": "策略八 – 個性",
      "page": 185,
      "excerpt": "屬性擁有權，例如 TAG 擁有「洗禮儀式」的屬性，並不容易達成。它 需要兩件事，也就是專注和犧牲。 在創立初期，TAG 投入大量資源，致力於研發下一代製作效果，無論白 天還是月光下都能讓觀眾驚艷。因此，他們幾乎沒有時間處理其他類型 的活動，且多次不得不婉拒。 當一家公司（像 TAG）專注於其最擅長的領域時，最終它將在產業中擁 有強大的特質。 Differentiate 208.Differentiate 208./20 下午5：33：/20 下午5：33：04 章節 16 Differentiate 208.indd 206 2 月 19 日 Differentiate 208.indd 206 2 月 19 日 2008/20 下午5：33：/20 下午5：33：04 策略八 – 個性 Differentiate .indd 207 Differentiate .indd /20 下午5：33：/20 下午5：33：04 你往往會記住個性鮮明、專注明確的人，因為這些人給人的印象是他們 知道自己是誰、想要什麼以及未來的方向。他們不一定是好人，但他們 強烈的個性讓他們很突出。 品牌也是一樣。擁有強烈個性的品牌會讓你印象深刻，你會記得他們。 所以，個性是讓你品牌與眾不同的一種方式。然而，並非所有品牌都適 合這種差異化。 服務品牌通常是最合適的，儘管也有許多產品品牌成功利用個性作為主 要差異化。 許多品牌設計師會把個性和特質混淆。因此，你常會發現，當品牌特質 被定義時，有些所謂的特質其實是個性。這讓整個過程變得非常混亂。 屬性與個性相關，但各自有其獨特的特徵。 Dictionary.com 將「人格」定義為：「 個人身體、 心理、情感及社會 特質的總和。 個體行為特徵的有組織模式。」 個性比屬性複雜得多，因為它涉及心理學，而屬性則比較像是身體特 徵。 一個品牌的個性關乎其本質，而這其實是極其複雜的量化。和所有成功 的品牌塑造一樣，關鍵在於簡化個性，讓它更容易被傳達。 我們不是指簡化你的產品或服務，而是你的個性。非常複雜的產品或服 務有時也能透過品牌個性的簡單表達來有效傳達。例如，西南航空試圖 展現開朗的個性，而聯合航空則在 2008 年 2 月 19 日出現 Differentiate 19 Feb 08.indd /20 下午5：33：/20 下午5：33：05 策略八號 – 人格209 多年來，他試圖以「Fly The Friendly Skies」為標語展現親切的個性。 要將個性作為差異化——也就是屬性所有權——你需要抓住一個個性， 並用它來區隔你的品牌。個性也是互斥的。同一類別內的兩個品牌，不 能用相同的個性來區分彼此。如果 iPod 是 MP3 播放器的經典品牌，那 麼其他播放器就得用不同的個性。 精神分裂症品牌 你不能試圖投射出多重個性。有些公司貪婪或無知，試圖成為一個溫"
    },
    {
      "title": "策略九 - 相反立場",
      "page": 199,
      "excerpt": "2008/20 下午5：33：05 章節 17 Differentiate 208.indd 222 2 月 19 日 Differentiate 208.indd 222 2 月 19 日 2008/20 下午5：33：/20 下午5：33：05 策略第九號 – 相反位置 Differentiate .indd 223"
    },
    {
      "title": "策略第十號 – 專業化",
      "page": 216,
      "excerpt": "2008/20 下午5：33：/20 下午5：33：07 章節 18 Differentiate .indd 240 Differentiate .indd /20 下午5：33：/20 下午5：33：07 策略第十號 – 專業化 Differentiate .indd 241 Differentiate .indd /20 下午5：33：/20 下午5：33：07 我們注意到大多數公司非常奇特的一點是，他們想成為通才，這樣就能 把所有東西賣給所有人。他們稱之為全方位防範。理論上聽起來不錯， 但在現實生活中並不總是能實現，因為人們往往認為專家知識較多或在 領域上更優秀。那麼，當利害關係重大時，你會怎麼做？你會從什麼都 賣的通才那裡買，還是從專家那裡買？除非你購買的東西其實並不那麼 重要——也就是說，錯誤的選擇不會對你的事業造成不利影響，否則你 大概會選擇專家。 舉例來說，如果你是為辦公室購買地板清潔劑，向通才或專科醫師購買 可能不太重要（除非你是經營醫院）。但當你購買一台重要的新防火牆 系統來保護伺服器免受駭客攻擊時，你很可能會想從防火牆專家那裡購 買。如果你沒別的事可做，一個有趣的消遣是觀察這些通才公司購買對 其業務至關重要的產品或服務。你可能會發現通才也傾向於向專家購 買！為什麼？ 因為他們認為專家比通才更優秀。這不是很有趣的現象嗎？想想看。當 你賣東西時，你試著把所有東西都賣掉。當你購買時，你應該從專門從 事你想購買的那種東西的人那裡購買。 觀察你自己的公司，以及它在嘗試賣出和買入時的行為。大概存在一種 傾向，想要對每個人都滿足一切。當企業面臨快速成長壓力時，許多企 業會傾向於延長生產線。想法是：我們賣出的產品越多，銷售收入就越 高。因此，看看新加坡交易所上市的公司會發現，許多公司從事各種無 關的業務。但當公司需要購買某項產品時，會選擇從通才還是專家那裡 購買？ Differentiate .indd 242 Differentiate .indd /20 下午5：33：/20 下午5：33：07 策略第十號 – 專業化243 專精是強而有力的差異化因素，因為人們通常認為專科醫師更有知識， 但成為專精醫師就必須專注。 有趣的是，我們的專注方向與大多數公司不同。 當我們在研討會上與公司會面時，我們喜歡問他們專注的領域是什麼。 許多人會給我們答案，例如：「喔，我們專注於四個領域。 第一，房地產開發。兩家，高級義大利餐廳。第三，奢侈品零售。第 四，廢棄物管理。這四大核心業務是我們專注的重點。」當我們聽到這 樣的話時，通常會忍不住想說：「哇，Nellie！」那根本不是專注。 「專注」就是你只做一件事。而你試著比世界上任何人都更擅長這件 事。當你擁有四個截然不同且互不相補的產業，如房地產、餐飲、零售 和廢棄物管理時，你就已經多元化了。 多元化教育有什麼不好？只要你夠大能完成，什麼都不行。多元化產業 需要大量的資金、資源和人力，只有大公司才能撥出這些資源。小型企 業需要專注於其核心業務。他們需要專精。但即使是大公司也應該專注 於自己的專業領域，因為多元化意味著你必須面對更多競爭者。以我們 前面提到的例子來說，這家公司很可能一開始是房地產開發，隨著時間 推移，逐漸擴展到餐飲、奢侈品和廢棄物管理。每次它拓展到新領域， 就會面臨更多（且截然不同的）競爭對手。這讓生活比原本更艱難。為 什麼？此外，80/20規則通常適用於像這樣的多元化教育公司。你常會"
    }
  ],
  "has_toc": true,
  "extracted_at": "2026-04-25"
}